{
  "startDate": "2026-01-13T08:45:40.985Z",
  "completionDate": "2026-01-13T08:54:21.771Z",
  "completionError": null,
  "unresolved": {},
  "resolved": {
    "00cbe414-0e86-4de3-8c1a-b2e319dfae26": {
      "task": {
        "id": "00cbe414-0e86-4de3-8c1a-b2e319dfae26",
        "parentId": null,
        "originatingTaskId": null,
        "username": "Alokzh",
        "since": "2026-01-05T00:00:00.000Z",
        "until": "2026-01-12T00:00:00.000Z",
        "term": "lfx-2025-term3-follow-up",
        "weekOf": "2026-01-05"
      }
    },
    "0187bfea-7ef4-41e7-ab1b-8c5611ca8073": {
      "task": {
        "id": "0187bfea-7ef4-41e7-ab1b-8c5611ca8073",
        "parentId": null,
        "originatingTaskId": null,
        "username": "Minimega12121",
        "since": "2026-01-05T00:00:00.000Z",
        "until": "2026-01-12T00:00:00.000Z",
        "term": "lfx-2025-term3-follow-up",
        "weekOf": "2026-01-05"
      }
    },
    "027778f8-96f8-48cd-87de-31cfb3c1e19a": {
      "task": {
        "id": "027778f8-96f8-48cd-87de-31cfb3c1e19a",
        "parentId": null,
        "originatingTaskId": null,
        "username": "shivkr6",
        "since": "2026-01-05T00:00:00.000Z",
        "until": "2026-01-12T00:00:00.000Z",
        "term": "lfx-2025-term3-follow-up",
        "weekOf": "2026-01-05"
      }
    },
    "02e577e4-bfd2-4de9-b70a-60a2f350ab0f": {
      "task": {
        "id": "02e577e4-bfd2-4de9-b70a-60a2f350ab0f",
        "parentId": null,
        "originatingTaskId": null,
        "username": "hari45678",
        "since": "2026-01-05T00:00:00.000Z",
        "until": "2026-01-12T00:00:00.000Z",
        "term": "lfx-2025-term1-follow-up",
        "weekOf": "2026-01-05"
      }
    },
    "05161141-55e0-4c85-919e-d80affe35bd1": {
      "task": {
        "id": "05161141-55e0-4c85-919e-d80affe35bd1",
        "parentId": null,
        "originatingTaskId": null,
        "username": "MayorFaj",
        "since": "2026-01-05T00:00:00.000Z",
        "until": "2026-01-12T00:00:00.000Z",
        "term": "lfx-2025-term2-follow-up",
        "weekOf": "2026-01-05"
      }
    },
    "08dafa1c-e2f0-4c97-b459-d29d7b57f62e": {
      "task": {
        "id": "08dafa1c-e2f0-4c97-b459-d29d7b57f62e",
        "parentId": null,
        "originatingTaskId": null,
        "username": "liaolecheng",
        "since": "2026-01-05T00:00:00.000Z",
        "until": "2026-01-12T00:00:00.000Z",
        "term": "lfx-2025-term3-follow-up",
        "weekOf": "2026-01-05"
      }
    },
    "0911e103-95a9-4dd8-b0b4-40ac05a12fe5": {
      "task": {
        "id": "0911e103-95a9-4dd8-b0b4-40ac05a12fe5",
        "parentId": null,
        "originatingTaskId": null,
        "username": "adwait-godbole",
        "since": "2026-01-05T00:00:00.000Z",
        "until": "2026-01-12T00:00:00.000Z",
        "term": "lfx-2025-term1-follow-up",
        "weekOf": "2026-01-05"
      }
    },
    "0a765f94-02c8-4890-a833-84329d05bacd": {
      "task": {
        "id": "0a765f94-02c8-4890-a833-84329d05bacd",
        "parentId": null,
        "originatingTaskId": null,
        "username": "SindhuSundar1213",
        "since": "2026-01-05T00:00:00.000Z",
        "until": "2026-01-12T00:00:00.000Z",
        "term": "lfx-2025-term1-follow-up",
        "weekOf": "2026-01-05"
      }
    },
    "0e6458a4-c7b2-4f7b-a462-09724ceebd32": {
      "task": {
        "id": "0e6458a4-c7b2-4f7b-a462-09724ceebd32",
        "parentId": null,
        "originatingTaskId": null,
        "username": "ashish111333",
        "since": "2026-01-05T00:00:00.000Z",
        "until": "2026-01-12T00:00:00.000Z",
        "term": "lfx-2025-term1-follow-up",
        "weekOf": "2026-01-05"
      }
    },
    "0e7c56f6-d9d9-4864-bf57-bccc2b68ae23": {
      "task": {
        "id": "0e7c56f6-d9d9-4864-bf57-bccc2b68ae23",
        "parentId": null,
        "originatingTaskId": null,
        "username": "Dhiren-Mhatre",
        "since": "2026-01-05T00:00:00.000Z",
        "until": "2026-01-12T00:00:00.000Z",
        "term": "lfx-2025-term1-follow-up",
        "weekOf": "2026-01-05"
      }
    },
    "1028f6d6-c796-49d8-9976-805bc70d977b": {
      "task": {
        "id": "1028f6d6-c796-49d8-9976-805bc70d977b",
        "parentId": null,
        "originatingTaskId": null,
        "username": "inosmeet",
        "since": "2026-01-05T00:00:00.000Z",
        "until": "2026-01-12T00:00:00.000Z",
        "term": "lfx-2025-term1-follow-up",
        "weekOf": "2026-01-05"
      }
    },
    "10f215e7-05ca-450e-aab8-63dee93e331a": {
      "task": {
        "id": "10f215e7-05ca-450e-aab8-63dee93e331a",
        "parentId": null,
        "originatingTaskId": null,
        "username": "ngvanthanggit",
        "since": "2026-01-05T00:00:00.000Z",
        "until": "2026-01-12T00:00:00.000Z",
        "term": "lfx-2025-term3-follow-up",
        "weekOf": "2026-01-05"
      }
    },
    "118bd694-b07e-4c8d-848a-05d1b01f4065": {
      "task": {
        "id": "118bd694-b07e-4c8d-848a-05d1b01f4065",
        "parentId": null,
        "originatingTaskId": null,
        "username": "karanngi ",
        "since": "2026-01-05T00:00:00.000Z",
        "until": "2026-01-12T00:00:00.000Z",
        "term": "lfx-2025-term2-follow-up",
        "weekOf": "2026-01-05"
      },
      "debug": "{\n  \"query\": \"query GetSummary($username: String!, $since: DateTime!, $until: DateTime!) {\\n    rateLimit {\\n        cost\\n        limit\\n        nodeCount\\n        remaining\\n        resetAt\\n        used\\n    }\\n    user(login:$username){\\n        login\\n        name\\n        contributionsCollection(from:$since, to:$until){\\n            startedAt\\n            endedAt\\n            hasAnyContributions\\n\\n            totalCommitContributions\\n            totalIssueContributions\\n            totalPullRequestContributions\\n            totalPullRequestReviewContributions\\n\\n            totalRepositoriesWithContributedCommits\\n            totalRepositoriesWithContributedIssues\\n\\n\\n            commitContributionsByRepository(maxRepositories:100){\\n                repository{\\n                    owner{\\n                        login\\n                    }\\n                    nameWithOwner\\n                    url\\n                }\\n                url\\n                contributions(first:100){\\n                    pageInfo{\\n                        hasNextPage\\n                    }\\n                    totalCount\\n                }\\n            }\\n            issueContributionsByRepository(maxRepositories:100){\\n                repository{\\n                    owner{\\n                        login\\n                    }\\n                    nameWithOwner\\n                    url\\n                }\\n                contributions(first:100){\\n                    pageInfo{\\n                        hasNextPage\\n                    }\\n                    totalCount\\n                    nodes{\\n                        issue{\\n                            number\\n                        }\\n                    }\\n                }\\n            }\\n            pullRequestContributionsByRepository(maxRepositories:100){\\n                repository{\\n                    owner{\\n                        login\\n                    }\\n                    nameWithOwner\\n                    url\\n                }\\n                contributions(first:100){\\n                    pageInfo{\\n                        hasNextPage\\n                    }\\n                    totalCount\\n                    nodes{\\n                        pullRequest{\\n                            number\\n                        }\\n                    }\\n                }\\n            }\\n            pullRequestReviewContributionsByRepository(maxRepositories:100){\\n                repository{\\n                    owner{\\n                        login\\n                    }\\n                    nameWithOwner\\n                    url\\n                }\\n                contributions(first:100){\\n                    pageInfo{\\n                        hasNextPage\\n                    }\\n                    totalCount\\n                    nodes{\\n                        pullRequestReview{\\n                            url\\n                            pullRequest{\\n                                number\\n                            }\\n                        }\\n                    }\\n                }\\n            }\\n        }\\n    }\\n}\",\n  \"variables\": {\n    \"username\": \"karanngi \",\n    \"since\": \"2026-01-05T00:00:00.000Z\",\n    \"until\": \"2026-01-12T00:00:00.000Z\"\n  }\n}",
      "nonCriticalError": {
        "message": "Error in task 118bd694-b07e-4c8d-848a-05d1b01f4065: Request failed due to following response errors:\n - Could not resolve to a User with the login of 'karanngi '.. Headers: {\"access-control-allow-origin\":\"*\",\"access-control-expose-headers\":\"ETag, Link, Location, Retry-After, X-GitHub-OTP, X-RateLimit-Limit, X-RateLimit-Remaining, X-RateLimit-Used, X-RateLimit-Resource, X-RateLimit-Reset, X-OAuth-Scopes, X-Accepted-OAuth-Scopes, X-Poll-Interval, X-GitHub-Media-Type, X-GitHub-SSO, X-GitHub-Request-Id, Deprecation, Sunset\",\"connection\":\"close\",\"content-encoding\":\"gzip\",\"content-security-policy\":\"default-src 'none'\",\"content-type\":\"application/json; charset=utf-8\",\"date\":\"Tue, 13 Jan 2026 08:46:01 GMT\",\"referrer-policy\":\"origin-when-cross-origin, strict-origin-when-cross-origin\",\"server\":\"github.com\",\"strict-transport-security\":\"max-age=31536000; includeSubdomains; preload\",\"transfer-encoding\":\"chunked\",\"vary\":\"Accept-Encoding, Accept, X-Requested-With\",\"x-accepted-oauth-scopes\":\"repo\",\"x-content-type-options\":\"nosniff\",\"x-frame-options\":\"deny\",\"x-github-media-type\":\"github.v3; format=json\",\"x-github-request-id\":\"6456:387B09:137C9B:563CD2:69660649\",\"x-oauth-scopes\":\"public_repo, read:org, read:user, repo:status, user:email\",\"x-ratelimit-limit\":\"5000\",\"x-ratelimit-remaining\":\"4987\",\"x-ratelimit-reset\":\"1768297541\",\"x-ratelimit-resource\":\"graphql\",\"x-ratelimit-used\":\"13\",\"x-xss-protection\":\"0\"}. Error: Could not resolve to a User with the login of 'karanngi '.. Data: {\"rateLimit\":{\"cost\":1,\"limit\":5000,\"nodeCount\":400,\"remaining\":4987,\"resetAt\":\"2026-01-13T09:45:41Z\",\"used\":13},\"user\":null}.",
        "date": "2026-01-13T08:46:01.385Z"
      }
    },
    "121fd09a-efc1-4f55-95f0-0bf226165eb6": {
      "task": {
        "id": "121fd09a-efc1-4f55-95f0-0bf226165eb6",
        "parentId": null,
        "originatingTaskId": null,
        "username": "bearslyricattack",
        "since": "2026-01-05T00:00:00.000Z",
        "until": "2026-01-12T00:00:00.000Z",
        "term": "lfx-2025-term2-follow-up",
        "weekOf": "2026-01-05"
      }
    },
    "131247f6-62ec-4f8a-a1e3-4e11ae1e3d76": {
      "task": {
        "id": "131247f6-62ec-4f8a-a1e3-4e11ae1e3d76",
        "parentId": null,
        "originatingTaskId": null,
        "username": "amitamrutiya",
        "since": "2026-01-05T00:00:00.000Z",
        "until": "2026-01-12T00:00:00.000Z",
        "term": "lfx-2025-term1-follow-up",
        "weekOf": "2026-01-05"
      }
    },
    "138a9678-e635-4e73-a6e4-e8fb9c96bd46": {
      "task": {
        "id": "138a9678-e635-4e73-a6e4-e8fb9c96bd46",
        "parentId": null,
        "originatingTaskId": null,
        "username": "de6p",
        "since": "2026-01-05T00:00:00.000Z",
        "until": "2026-01-12T00:00:00.000Z",
        "term": "lfx-2025-term2-follow-up",
        "weekOf": "2026-01-05"
      }
    },
    "13aca7a0-8c11-4edc-a0c5-c53bac8687a5": {
      "task": {
        "id": "13aca7a0-8c11-4edc-a0c5-c53bac8687a5",
        "parentId": null,
        "originatingTaskId": null,
        "username": "7h3-3mp7y-m4n",
        "since": "2026-01-05T00:00:00.000Z",
        "until": "2026-01-12T00:00:00.000Z",
        "term": "lfx-2025-term1-follow-up",
        "weekOf": "2026-01-05"
      }
    },
    "14255796-28a0-4153-9f11-f8b1b15e5ba0": {
      "task": {
        "id": "14255796-28a0-4153-9f11-f8b1b15e5ba0",
        "parentId": null,
        "originatingTaskId": null,
        "username": "rizul2108",
        "since": "2026-01-05T00:00:00.000Z",
        "until": "2026-01-12T00:00:00.000Z",
        "term": "lfx-2025-term1-follow-up",
        "weekOf": "2026-01-05"
      }
    },
    "15ad59c7-ba0a-466a-8fc4-1a45287cd518": {
      "task": {
        "id": "15ad59c7-ba0a-466a-8fc4-1a45287cd518",
        "parentId": null,
        "originatingTaskId": null,
        "username": "ani1609",
        "since": "2026-01-05T00:00:00.000Z",
        "until": "2026-01-12T00:00:00.000Z",
        "term": "lfx-2025-term3-follow-up",
        "weekOf": "2026-01-05"
      }
    },
    "19281c3e-6e69-4eb3-96f5-a46f1b04d648": {
      "task": {
        "id": "19281c3e-6e69-4eb3-96f5-a46f1b04d648",
        "parentId": null,
        "originatingTaskId": null,
        "username": "LegGasai",
        "since": "2026-01-05T00:00:00.000Z",
        "until": "2026-01-12T00:00:00.000Z",
        "term": "lfx-2025-term1-follow-up",
        "weekOf": "2026-01-05"
      }
    },
    "1a70a233-92bf-4007-bdfc-20e49912ecb8": {
      "task": {
        "id": "1a70a233-92bf-4007-bdfc-20e49912ecb8",
        "parentId": null,
        "originatingTaskId": null,
        "username": "AryanNanda17",
        "since": "2026-01-05T00:00:00.000Z",
        "until": "2026-01-12T00:00:00.000Z",
        "term": "lfx-2025-term1-follow-up",
        "weekOf": "2026-01-05"
      }
    },
    "1d9c52f9-fa1c-4986-af67-50d7f7cd3250": {
      "task": {
        "id": "1d9c52f9-fa1c-4986-af67-50d7f7cd3250",
        "parentId": null,
        "originatingTaskId": null,
        "username": "jayesh9747",
        "since": "2026-01-05T00:00:00.000Z",
        "until": "2026-01-12T00:00:00.000Z",
        "term": "lfx-2025-term1-follow-up",
        "weekOf": "2026-01-05"
      }
    },
    "1df1fdeb-6a05-4f98-8386-e02f987e6ab3": {
      "task": {
        "id": "1df1fdeb-6a05-4f98-8386-e02f987e6ab3",
        "parentId": null,
        "originatingTaskId": null,
        "username": "Rxinui",
        "since": "2026-01-05T00:00:00.000Z",
        "until": "2026-01-12T00:00:00.000Z",
        "term": "lfx-2025-term2-follow-up",
        "weekOf": "2026-01-05"
      }
    },
    "218e4295-27b2-472e-8a79-3275206cfc60": {
      "task": {
        "id": "218e4295-27b2-472e-8a79-3275206cfc60",
        "parentId": null,
        "originatingTaskId": null,
        "username": "entlein",
        "since": "2026-01-05T00:00:00.000Z",
        "until": "2026-01-12T00:00:00.000Z",
        "term": "lfx-2025-term3-follow-up",
        "weekOf": "2026-01-05"
      }
    },
    "21dfdf49-2dd7-4f21-bd0f-315f477bd0ba": {
      "task": {
        "id": "21dfdf49-2dd7-4f21-bd0f-315f477bd0ba",
        "parentId": null,
        "originatingTaskId": null,
        "username": "sancppp",
        "since": "2026-01-05T00:00:00.000Z",
        "until": "2026-01-12T00:00:00.000Z",
        "term": "lfx-2025-term1-follow-up",
        "weekOf": "2026-01-05"
      }
    },
    "23ba9b66-3916-4344-ae39-2990cf11e934": {
      "task": {
        "id": "23ba9b66-3916-4344-ae39-2990cf11e934",
        "parentId": null,
        "originatingTaskId": null,
        "username": "kagaya85",
        "since": "2026-01-05T00:00:00.000Z",
        "until": "2026-01-12T00:00:00.000Z",
        "term": "lfx-2025-term2-follow-up",
        "weekOf": "2026-01-05"
      }
    },
    "27764180-3798-4313-84b2-30bfbb832c9f": {
      "task": {
        "id": "27764180-3798-4313-84b2-30bfbb832c9f",
        "parentId": null,
        "originatingTaskId": null,
        "username": "Rupam-It",
        "since": "2026-01-05T00:00:00.000Z",
        "until": "2026-01-12T00:00:00.000Z",
        "term": "lfx-2025-term2-follow-up",
        "weekOf": "2026-01-05"
      }
    },
    "2b611838-a474-482c-af95-b71fdfc46767": {
      "task": {
        "id": "2b611838-a474-482c-af95-b71fdfc46767",
        "parentId": null,
        "originatingTaskId": null,
        "username": "zhengkezhou1",
        "since": "2026-01-05T00:00:00.000Z",
        "until": "2026-01-12T00:00:00.000Z",
        "term": "lfx-2025-term2-follow-up",
        "weekOf": "2026-01-05"
      }
    },
    "2ba677b3-cf54-4cf5-8e99-c05cf25a43ee": {
      "task": {
        "id": "2ba677b3-cf54-4cf5-8e99-c05cf25a43ee",
        "parentId": null,
        "originatingTaskId": null,
        "username": "Transcendental-Programmer",
        "since": "2026-01-05T00:00:00.000Z",
        "until": "2026-01-12T00:00:00.000Z",
        "term": "lfx-2025-term3-follow-up",
        "weekOf": "2026-01-05"
      }
    },
    "2cbbec7b-d644-4a75-b812-da449f48452d": {
      "task": {
        "id": "2cbbec7b-d644-4a75-b812-da449f48452d",
        "parentId": null,
        "originatingTaskId": null,
        "username": "useradityaa",
        "since": "2026-01-05T00:00:00.000Z",
        "until": "2026-01-12T00:00:00.000Z",
        "term": "lfx-2025-term2-follow-up",
        "weekOf": "2026-01-05"
      }
    },
    "2de129d6-5e8b-442e-a505-3bfc4fc16f63": {
      "task": {
        "id": "2de129d6-5e8b-442e-a505-3bfc4fc16f63",
        "parentId": null,
        "originatingTaskId": null,
        "username": "gaurab-khanal",
        "since": "2026-01-05T00:00:00.000Z",
        "until": "2026-01-12T00:00:00.000Z",
        "term": "lfx-2025-term3-follow-up",
        "weekOf": "2026-01-05"
      }
    },
    "2f915d8f-f98e-4e56-92b2-8b12d6cce962": {
      "task": {
        "id": "2f915d8f-f98e-4e56-92b2-8b12d6cce962",
        "parentId": null,
        "originatingTaskId": null,
        "username": "Ajay-singh1",
        "since": "2026-01-05T00:00:00.000Z",
        "until": "2026-01-12T00:00:00.000Z",
        "term": "lfx-2025-term2-follow-up",
        "weekOf": "2026-01-05"
      }
    },
    "366e2473-5ef6-4a16-91b8-8b18a8791e64": {
      "task": {
        "id": "366e2473-5ef6-4a16-91b8-8b18a8791e64",
        "parentId": null,
        "originatingTaskId": null,
        "username": "RONAK-AI647",
        "since": "2026-01-05T00:00:00.000Z",
        "until": "2026-01-12T00:00:00.000Z",
        "term": "lfx-2025-term3-follow-up",
        "weekOf": "2026-01-05"
      }
    },
    "37e52a7a-6cbb-4de2-b5fe-818af76e63c6": {
      "task": {
        "id": "37e52a7a-6cbb-4de2-b5fe-818af76e63c6",
        "parentId": null,
        "originatingTaskId": null,
        "username": "DhairyaMajmudar",
        "since": "2026-01-05T00:00:00.000Z",
        "until": "2026-01-12T00:00:00.000Z",
        "term": "lfx-2025-term1-follow-up",
        "weekOf": "2026-01-05"
      }
    },
    "39dbaf7a-6c4a-437a-b95a-c7ff60d97967": {
      "task": {
        "id": "39dbaf7a-6c4a-437a-b95a-c7ff60d97967",
        "parentId": null,
        "originatingTaskId": null,
        "username": "chaospan",
        "since": "2026-01-05T00:00:00.000Z",
        "until": "2026-01-12T00:00:00.000Z",
        "term": "lfx-2025-term2-follow-up",
        "weekOf": "2026-01-05"
      }
    },
    "39f9db9f-cf99-47d3-ae11-d55362b0f0de": {
      "task": {
        "id": "39f9db9f-cf99-47d3-ae11-d55362b0f0de",
        "parentId": null,
        "originatingTaskId": null,
        "username": "upsaurav12",
        "since": "2026-01-05T00:00:00.000Z",
        "until": "2026-01-12T00:00:00.000Z",
        "term": "lfx-2025-term2-follow-up",
        "weekOf": "2026-01-05"
      }
    },
    "3b4d5fa5-7872-4196-b3ab-fa5b9e8c9004": {
      "task": {
        "id": "3b4d5fa5-7872-4196-b3ab-fa5b9e8c9004",
        "parentId": null,
        "originatingTaskId": null,
        "username": "kadai0308",
        "since": "2026-01-05T00:00:00.000Z",
        "until": "2026-01-12T00:00:00.000Z",
        "term": "lfx-2025-term2-follow-up",
        "weekOf": "2026-01-05"
      }
    },
    "3c23b7ab-85a4-4de9-8d23-924239bfacc2": {
      "task": {
        "id": "3c23b7ab-85a4-4de9-8d23-924239bfacc2",
        "parentId": null,
        "originatingTaskId": null,
        "username": "Kunal-511",
        "since": "2026-01-05T00:00:00.000Z",
        "until": "2026-01-12T00:00:00.000Z",
        "term": "lfx-2025-term1-follow-up",
        "weekOf": "2026-01-05"
      }
    },
    "3c71a21e-0101-4b51-93fd-2b926c32c485": {
      "task": {
        "id": "3c71a21e-0101-4b51-93fd-2b926c32c485",
        "parentId": null,
        "originatingTaskId": null,
        "username": "AryanBakliwal",
        "since": "2026-01-05T00:00:00.000Z",
        "until": "2026-01-12T00:00:00.000Z",
        "term": "lfx-2025-term1-follow-up",
        "weekOf": "2026-01-05"
      }
    },
    "3ec47b59-beb4-41b3-a865-8a5e781eb614": {
      "task": {
        "id": "3ec47b59-beb4-41b3-a865-8a5e781eb614",
        "parentId": null,
        "originatingTaskId": null,
        "username": "Daksh1603",
        "since": "2026-01-05T00:00:00.000Z",
        "until": "2026-01-12T00:00:00.000Z",
        "term": "lfx-2025-term3-follow-up",
        "weekOf": "2026-01-05"
      }
    },
    "4220d383-5506-4156-a01b-174018a1cff1": {
      "task": {
        "id": "4220d383-5506-4156-a01b-174018a1cff1",
        "parentId": null,
        "originatingTaskId": null,
        "username": "chahatsagarmain",
        "since": "2026-01-05T00:00:00.000Z",
        "until": "2026-01-12T00:00:00.000Z",
        "term": "lfx-2025-term2-follow-up",
        "weekOf": "2026-01-05"
      }
    },
    "4227e89b-fcde-43ac-a79e-762b04aae5e3": {
      "task": {
        "id": "4227e89b-fcde-43ac-a79e-762b04aae5e3",
        "parentId": null,
        "originatingTaskId": null,
        "username": "supreme-gg-gg",
        "since": "2026-01-05T00:00:00.000Z",
        "until": "2026-01-12T00:00:00.000Z",
        "term": "lfx-2025-term3-follow-up",
        "weekOf": "2026-01-05"
      }
    },
    "43b23356-a55f-4398-b3a8-fa710a47ecf8": {
      "task": {
        "id": "43b23356-a55f-4398-b3a8-fa710a47ecf8",
        "parentId": null,
        "originatingTaskId": null,
        "username": "Siddhi-agg",
        "since": "2026-01-05T00:00:00.000Z",
        "until": "2026-01-12T00:00:00.000Z",
        "term": "lfx-2025-term1-follow-up",
        "weekOf": "2026-01-05"
      }
    },
    "44911587-0da5-4e9b-b645-7c44751c1fd8": {
      "task": {
        "id": "44911587-0da5-4e9b-b645-7c44751c1fd8",
        "parentId": null,
        "originatingTaskId": null,
        "username": "Khushmagrawal",
        "since": "2026-01-05T00:00:00.000Z",
        "until": "2026-01-12T00:00:00.000Z",
        "term": "lfx-2025-term2-follow-up",
        "weekOf": "2026-01-05"
      }
    },
    "45aa6055-4d02-45ac-8860-62cd398b0cb7": {
      "task": {
        "id": "45aa6055-4d02-45ac-8860-62cd398b0cb7",
        "parentId": null,
        "originatingTaskId": null,
        "username": "d-aggarwal",
        "since": "2026-01-05T00:00:00.000Z",
        "until": "2026-01-12T00:00:00.000Z",
        "term": "lfx-2025-term2-follow-up",
        "weekOf": "2026-01-05"
      }
    },
    "4608c969-af1d-4ad7-acae-4fe8d158bb37": {
      "task": {
        "id": "4608c969-af1d-4ad7-acae-4fe8d158bb37",
        "parentId": null,
        "originatingTaskId": null,
        "username": "eeshaanSA",
        "since": "2026-01-05T00:00:00.000Z",
        "until": "2026-01-12T00:00:00.000Z",
        "term": "lfx-2025-term3-follow-up",
        "weekOf": "2026-01-05"
      }
    },
    "476fe81f-1d99-4b68-84f3-3d725b74f535": {
      "task": {
        "id": "476fe81f-1d99-4b68-84f3-3d725b74f535",
        "parentId": null,
        "originatingTaskId": null,
        "username": "Sagar2366",
        "since": "2026-01-05T00:00:00.000Z",
        "until": "2026-01-12T00:00:00.000Z",
        "term": "lfx-2025-term3-follow-up",
        "weekOf": "2026-01-05"
      }
    },
    "47ad8165-5d6c-474c-874d-86dbe1990542": {
      "task": {
        "id": "47ad8165-5d6c-474c-874d-86dbe1990542",
        "parentId": null,
        "originatingTaskId": null,
        "username": "suhyenim",
        "since": "2026-01-05T00:00:00.000Z",
        "until": "2026-01-12T00:00:00.000Z",
        "term": "lfx-2025-term1-follow-up",
        "weekOf": "2026-01-05"
      }
    },
    "485ca042-0da4-484f-be2e-49b39b48166b": {
      "task": {
        "id": "485ca042-0da4-484f-be2e-49b39b48166b",
        "parentId": null,
        "originatingTaskId": null,
        "username": "Arshdeep54",
        "since": "2026-01-05T00:00:00.000Z",
        "until": "2026-01-12T00:00:00.000Z",
        "term": "lfx-2025-term3-follow-up",
        "weekOf": "2026-01-05"
      }
    },
    "49260f44-c38b-4e5a-b8bf-01818e6df41f": {
      "task": {
        "id": "49260f44-c38b-4e5a-b8bf-01818e6df41f",
        "parentId": null,
        "originatingTaskId": null,
        "username": "ElectricFish7",
        "since": "2026-01-05T00:00:00.000Z",
        "until": "2026-01-12T00:00:00.000Z",
        "term": "lfx-2025-term1-follow-up",
        "weekOf": "2026-01-05"
      }
    },
    "49809c13-9e3d-4b02-b4e4-bdc6d3f9bca2": {
      "task": {
        "id": "49809c13-9e3d-4b02-b4e4-bdc6d3f9bca2",
        "parentId": null,
        "originatingTaskId": null,
        "username": "tiansuo114",
        "since": "2026-01-05T00:00:00.000Z",
        "until": "2026-01-12T00:00:00.000Z",
        "term": "lfx-2025-term1-follow-up",
        "weekOf": "2026-01-05"
      }
    },
    "4a7149fd-4c8f-4968-bcca-36f958c13eec": {
      "task": {
        "id": "4a7149fd-4c8f-4968-bcca-36f958c13eec",
        "parentId": null,
        "originatingTaskId": null,
        "username": "arctic-beep",
        "since": "2026-01-05T00:00:00.000Z",
        "until": "2026-01-12T00:00:00.000Z",
        "term": "lfx-2025-term2-follow-up",
        "weekOf": "2026-01-05"
      }
    },
    "4e221a66-483e-43ad-b983-69406b7d3f0c": {
      "task": {
        "id": "4e221a66-483e-43ad-b983-69406b7d3f0c",
        "parentId": null,
        "originatingTaskId": null,
        "username": "owenowenisme",
        "since": "2026-01-05T00:00:00.000Z",
        "until": "2026-01-12T00:00:00.000Z",
        "term": "lfx-2025-term3-follow-up",
        "weekOf": "2026-01-05"
      }
    },
    "4f718465-3335-4799-89f3-925f8724826b": {
      "task": {
        "id": "4f718465-3335-4799-89f3-925f8724826b",
        "parentId": null,
        "originatingTaskId": null,
        "username": "Harsh4902",
        "since": "2026-01-05T00:00:00.000Z",
        "until": "2026-01-12T00:00:00.000Z",
        "term": "lfx-2025-term1-follow-up",
        "weekOf": "2026-01-05"
      }
    },
    "50e64b3d-6cb2-44a0-91f3-57e7b3a665a2": {
      "task": {
        "id": "50e64b3d-6cb2-44a0-91f3-57e7b3a665a2",
        "parentId": null,
        "originatingTaskId": null,
        "username": "faakhir30",
        "since": "2026-01-05T00:00:00.000Z",
        "until": "2026-01-12T00:00:00.000Z",
        "term": "lfx-2025-term1-follow-up",
        "weekOf": "2026-01-05"
      }
    },
    "52131ffa-941a-41ee-99f2-b6c433c567ab": {
      "task": {
        "id": "52131ffa-941a-41ee-99f2-b6c433c567ab",
        "parentId": null,
        "originatingTaskId": null,
        "username": "naman9271",
        "since": "2026-01-05T00:00:00.000Z",
        "until": "2026-01-12T00:00:00.000Z",
        "term": "lfx-2025-term3-follow-up",
        "weekOf": "2026-01-05"
      }
    },
    "526cc51f-ca7a-44b1-8f94-7ffeafb5c906": {
      "task": {
        "id": "526cc51f-ca7a-44b1-8f94-7ffeafb5c906",
        "parentId": null,
        "originatingTaskId": null,
        "username": "FaheemOnHub",
        "since": "2026-01-05T00:00:00.000Z",
        "until": "2026-01-12T00:00:00.000Z",
        "term": "lfx-2025-term2-follow-up",
        "weekOf": "2026-01-05"
      }
    },
    "53e0eaed-1b3c-40ec-b5b5-37048aec7e5b": {
      "task": {
        "id": "53e0eaed-1b3c-40ec-b5b5-37048aec7e5b",
        "parentId": null,
        "originatingTaskId": null,
        "username": "Nupurshivani",
        "since": "2026-01-05T00:00:00.000Z",
        "until": "2026-01-12T00:00:00.000Z",
        "term": "lfx-2025-term3-follow-up",
        "weekOf": "2026-01-05"
      }
    },
    "5a12b95d-df9f-4716-8a1d-e5ff7f56397b": {
      "task": {
        "id": "5a12b95d-df9f-4716-8a1d-e5ff7f56397b",
        "parentId": null,
        "originatingTaskId": null,
        "username": "spa-raj",
        "since": "2026-01-05T00:00:00.000Z",
        "until": "2026-01-12T00:00:00.000Z",
        "term": "lfx-2025-term3-follow-up",
        "weekOf": "2026-01-05"
      }
    },
    "5b9153c2-de75-41f4-82f7-74caf399ba50": {
      "task": {
        "id": "5b9153c2-de75-41f4-82f7-74caf399ba50",
        "parentId": null,
        "originatingTaskId": null,
        "username": "pangfufuf",
        "since": "2026-01-05T00:00:00.000Z",
        "until": "2026-01-12T00:00:00.000Z",
        "term": "lfx-2025-term3-follow-up",
        "weekOf": "2026-01-05"
      }
    },
    "5d19d6d9-5cbd-47e8-b491-52bc618e8c71": {
      "task": {
        "id": "5d19d6d9-5cbd-47e8-b491-52bc618e8c71",
        "parentId": null,
        "originatingTaskId": null,
        "username": "Rishab87",
        "since": "2026-01-05T00:00:00.000Z",
        "until": "2026-01-12T00:00:00.000Z",
        "term": "lfx-2025-term3-follow-up",
        "weekOf": "2026-01-05"
      }
    },
    "5e161871-f338-467a-8142-f0b198b1b344": {
      "task": {
        "id": "5e161871-f338-467a-8142-f0b198b1b344",
        "parentId": null,
        "originatingTaskId": null,
        "username": "RayyanSeliya",
        "since": "2026-01-05T00:00:00.000Z",
        "until": "2026-01-12T00:00:00.000Z",
        "term": "lfx-2025-term3-follow-up",
        "weekOf": "2026-01-05"
      }
    },
    "5ec76e3d-4823-4073-b9a4-ea0d6d1f08fa": {
      "task": {
        "id": "5ec76e3d-4823-4073-b9a4-ea0d6d1f08fa",
        "parentId": null,
        "originatingTaskId": null,
        "username": "yp969803",
        "since": "2026-01-05T00:00:00.000Z",
        "until": "2026-01-12T00:00:00.000Z",
        "term": "lfx-2025-term1-follow-up",
        "weekOf": "2026-01-05"
      }
    },
    "5eef72e8-12f3-488f-a9be-5d888b9fd000": {
      "task": {
        "id": "5eef72e8-12f3-488f-a9be-5d888b9fd000",
        "parentId": null,
        "originatingTaskId": null,
        "username": "mrmerlin320",
        "since": "2026-01-05T00:00:00.000Z",
        "until": "2026-01-12T00:00:00.000Z",
        "term": "lfx-2025-term1-follow-up",
        "weekOf": "2026-01-05"
      }
    },
    "6065174f-b439-4595-8041-18b5d645cfc2": {
      "task": {
        "id": "6065174f-b439-4595-8041-18b5d645cfc2",
        "parentId": null,
        "originatingTaskId": null,
        "username": "pipiland2612",
        "since": "2026-01-05T00:00:00.000Z",
        "until": "2026-01-12T00:00:00.000Z",
        "term": "lfx-2025-term3-follow-up",
        "weekOf": "2026-01-05"
      }
    },
    "64b2cbf9-588b-4d7e-8419-6d798d60986c": {
      "task": {
        "id": "64b2cbf9-588b-4d7e-8419-6d798d60986c",
        "parentId": null,
        "originatingTaskId": null,
        "username": "corsairier",
        "since": "2026-01-05T00:00:00.000Z",
        "until": "2026-01-12T00:00:00.000Z",
        "term": "lfx-2025-term3-follow-up",
        "weekOf": "2026-01-05"
      }
    },
    "650325f3-58d6-4322-877c-ad114f342aa9": {
      "task": {
        "id": "650325f3-58d6-4322-877c-ad114f342aa9",
        "parentId": null,
        "originatingTaskId": null,
        "username": "dekaihu",
        "since": "2026-01-05T00:00:00.000Z",
        "until": "2026-01-12T00:00:00.000Z",
        "term": "lfx-2025-term3-follow-up",
        "weekOf": "2026-01-05"
      }
    },
    "65ac64b2-ffb5-46ff-83d0-78bcd99ce8c9": {
      "task": {
        "id": "65ac64b2-ffb5-46ff-83d0-78bcd99ce8c9",
        "parentId": null,
        "originatingTaskId": null,
        "username": "ankitajana21",
        "since": "2026-01-05T00:00:00.000Z",
        "until": "2026-01-12T00:00:00.000Z",
        "term": "lfx-2025-term1-follow-up",
        "weekOf": "2026-01-05"
      }
    },
    "685f921f-827f-4df4-b371-7f1e6abe5d1d": {
      "task": {
        "id": "685f921f-827f-4df4-b371-7f1e6abe5d1d",
        "parentId": null,
        "originatingTaskId": null,
        "username": "niladrix719",
        "since": "2026-01-05T00:00:00.000Z",
        "until": "2026-01-12T00:00:00.000Z",
        "term": "lfx-2025-term2-follow-up",
        "weekOf": "2026-01-05"
      }
    },
    "697bb75f-d6d7-48d7-9085-6fb2003d7af0": {
      "task": {
        "id": "697bb75f-d6d7-48d7-9085-6fb2003d7af0",
        "parentId": null,
        "originatingTaskId": null,
        "username": "Saumya40-codes",
        "since": "2026-01-05T00:00:00.000Z",
        "until": "2026-01-12T00:00:00.000Z",
        "term": "lfx-2025-term1-follow-up",
        "weekOf": "2026-01-05"
      }
    },
    "69cbebd0-66b9-420f-9916-7e0ff79c11b7": {
      "task": {
        "id": "69cbebd0-66b9-420f-9916-7e0ff79c11b7",
        "parentId": null,
        "originatingTaskId": null,
        "username": "sbegin0",
        "since": "2026-01-05T00:00:00.000Z",
        "until": "2026-01-12T00:00:00.000Z",
        "term": "lfx-2025-term1-follow-up",
        "weekOf": "2026-01-05"
      }
    },
    "6b8b5264-35f5-41c3-89f3-77055754fc87": {
      "task": {
        "id": "6b8b5264-35f5-41c3-89f3-77055754fc87",
        "parentId": null,
        "originatingTaskId": null,
        "username": "ItshMoh",
        "since": "2026-01-05T00:00:00.000Z",
        "until": "2026-01-12T00:00:00.000Z",
        "term": "lfx-2025-term2-follow-up",
        "weekOf": "2026-01-05"
      }
    },
    "6cc811ba-d5cd-4c9d-a623-ca7830d72102": {
      "task": {
        "id": "6cc811ba-d5cd-4c9d-a623-ca7830d72102",
        "parentId": null,
        "originatingTaskId": null,
        "username": "KapilSareen",
        "since": "2026-01-05T00:00:00.000Z",
        "until": "2026-01-12T00:00:00.000Z",
        "term": "lfx-2025-term1-follow-up",
        "weekOf": "2026-01-05"
      }
    },
    "6efde046-b77a-417b-ad2e-4701f9e09ca4": {
      "task": {
        "id": "6efde046-b77a-417b-ad2e-4701f9e09ca4",
        "parentId": null,
        "originatingTaskId": null,
        "username": "Manik2708",
        "since": "2026-01-05T00:00:00.000Z",
        "until": "2026-01-12T00:00:00.000Z",
        "term": "lfx-2025-term1-follow-up",
        "weekOf": "2026-01-05"
      }
    },
    "747abadc-77a4-472d-919d-ac53f702d952": {
      "task": {
        "id": "747abadc-77a4-472d-919d-ac53f702d952",
        "parentId": null,
        "originatingTaskId": null,
        "username": "Dakshjain1",
        "since": "2026-01-05T00:00:00.000Z",
        "until": "2026-01-12T00:00:00.000Z",
        "term": "lfx-2025-term1-follow-up",
        "weekOf": "2026-01-05"
      }
    },
    "74abe5b2-7f13-4dd0-bc84-b73c01e149f8": {
      "task": {
        "id": "74abe5b2-7f13-4dd0-bc84-b73c01e149f8",
        "parentId": null,
        "originatingTaskId": null,
        "username": "SkySingh04",
        "since": "2026-01-05T00:00:00.000Z",
        "until": "2026-01-12T00:00:00.000Z",
        "term": "lfx-2025-term1-follow-up",
        "weekOf": "2026-01-05"
      }
    },
    "750b27cc-eb5b-4d4d-90b4-733fabf02080": {
      "task": {
        "id": "750b27cc-eb5b-4d4d-90b4-733fabf02080",
        "parentId": null,
        "originatingTaskId": null,
        "username": "NA",
        "since": "2026-01-05T00:00:00.000Z",
        "until": "2026-01-12T00:00:00.000Z",
        "term": "lfx-2025-term3-follow-up",
        "weekOf": "2026-01-05"
      }
    },
    "7715f961-d9ff-49d8-ad06-e449242ad601": {
      "task": {
        "id": "7715f961-d9ff-49d8-ad06-e449242ad601",
        "parentId": null,
        "originatingTaskId": null,
        "username": "ravjot07",
        "since": "2026-01-05T00:00:00.000Z",
        "until": "2026-01-12T00:00:00.000Z",
        "term": "lfx-2025-term1-follow-up",
        "weekOf": "2026-01-05"
      }
    },
    "77bbdf34-71cc-42d8-b51d-fc7cb267443f": {
      "task": {
        "id": "77bbdf34-71cc-42d8-b51d-fc7cb267443f",
        "parentId": null,
        "originatingTaskId": null,
        "username": "Rohanraj123",
        "since": "2026-01-05T00:00:00.000Z",
        "until": "2026-01-12T00:00:00.000Z",
        "term": "lfx-2025-term2-follow-up",
        "weekOf": "2026-01-05"
      }
    },
    "7804a305-cd6c-408c-93f3-91be6c9af94c": {
      "task": {
        "id": "7804a305-cd6c-408c-93f3-91be6c9af94c",
        "parentId": null,
        "originatingTaskId": null,
        "username": "Namanv0509",
        "since": "2026-01-05T00:00:00.000Z",
        "until": "2026-01-12T00:00:00.000Z",
        "term": "lfx-2025-term3-follow-up",
        "weekOf": "2026-01-05"
      }
    },
    "7868f14b-fbc3-4333-9bc8-214d24dcd4d6": {
      "task": {
        "id": "7868f14b-fbc3-4333-9bc8-214d24dcd4d6",
        "parentId": null,
        "originatingTaskId": null,
        "username": "arnabnandikgp",
        "since": "2026-01-05T00:00:00.000Z",
        "until": "2026-01-12T00:00:00.000Z",
        "term": "lfx-2025-term1-follow-up",
        "weekOf": "2026-01-05"
      }
    },
    "78f6c8b9-c0c2-4676-aae4-200107c7c81e": {
      "task": {
        "id": "78f6c8b9-c0c2-4676-aae4-200107c7c81e",
        "parentId": null,
        "originatingTaskId": null,
        "username": "Manas23601",
        "since": "2026-01-05T00:00:00.000Z",
        "until": "2026-01-12T00:00:00.000Z",
        "term": "lfx-2025-term2-follow-up",
        "weekOf": "2026-01-05"
      }
    },
    "79f228dd-e360-4e45-857e-be2b2dc1492b": {
      "task": {
        "id": "79f228dd-e360-4e45-857e-be2b2dc1492b",
        "parentId": null,
        "originatingTaskId": null,
        "username": "AryanParashar24",
        "since": "2026-01-05T00:00:00.000Z",
        "until": "2026-01-12T00:00:00.000Z",
        "term": "lfx-2025-term3-follow-up",
        "weekOf": "2026-01-05"
      }
    },
    "7a3eb7e1-e92b-4a14-9da1-068b8bd485ee": {
      "task": {
        "id": "7a3eb7e1-e92b-4a14-9da1-068b8bd485ee",
        "parentId": null,
        "originatingTaskId": null,
        "username": "sakshikumar19",
        "since": "2026-01-05T00:00:00.000Z",
        "until": "2026-01-12T00:00:00.000Z",
        "term": "lfx-2025-term1-follow-up",
        "weekOf": "2026-01-05"
      }
    },
    "7acf44d3-8b98-45e1-8a4c-c6d9899b094b": {
      "task": {
        "id": "7acf44d3-8b98-45e1-8a4c-c6d9899b094b",
        "parentId": null,
        "originatingTaskId": null,
        "username": "alan910127",
        "since": "2026-01-05T00:00:00.000Z",
        "until": "2026-01-12T00:00:00.000Z",
        "term": "lfx-2025-term1-follow-up",
        "weekOf": "2026-01-05"
      }
    },
    "7d90d7b6-b214-4fcb-a958-e4a11e66a6df": {
      "task": {
        "id": "7d90d7b6-b214-4fcb-a958-e4a11e66a6df",
        "parentId": null,
        "originatingTaskId": null,
        "username": "LuluNwenyi",
        "since": "2026-01-05T00:00:00.000Z",
        "until": "2026-01-12T00:00:00.000Z",
        "term": "lfx-2025-term2-follow-up",
        "weekOf": "2026-01-05"
      }
    },
    "7db57125-e1ac-4830-adfb-718256149f4b": {
      "task": {
        "id": "7db57125-e1ac-4830-adfb-718256149f4b",
        "parentId": null,
        "originatingTaskId": null,
        "username": "abhinavs1920",
        "since": "2026-01-05T00:00:00.000Z",
        "until": "2026-01-12T00:00:00.000Z",
        "term": "lfx-2025-term3-follow-up",
        "weekOf": "2026-01-05"
      }
    },
    "7e486be3-fe84-4f0e-9098-2664239e5776": {
      "task": {
        "id": "7e486be3-fe84-4f0e-9098-2664239e5776",
        "parentId": null,
        "originatingTaskId": null,
        "username": "suqin9",
        "since": "2026-01-05T00:00:00.000Z",
        "until": "2026-01-12T00:00:00.000Z",
        "term": "lfx-2025-term1-follow-up",
        "weekOf": "2026-01-05"
      }
    },
    "800d6eef-4084-4d18-b5d9-11f4c1bb8912": {
      "task": {
        "id": "800d6eef-4084-4d18-b5d9-11f4c1bb8912",
        "parentId": null,
        "originatingTaskId": null,
        "username": "dev-liz",
        "since": "2026-01-05T00:00:00.000Z",
        "until": "2026-01-12T00:00:00.000Z",
        "term": "lfx-2025-term3-follow-up",
        "weekOf": "2026-01-05"
      }
    },
    "815e917b-ba4f-467a-ab61-29978b63aaf8": {
      "task": {
        "id": "815e917b-ba4f-467a-ab61-29978b63aaf8",
        "parentId": null,
        "originatingTaskId": null,
        "username": "g4rud4kun",
        "since": "2026-01-05T00:00:00.000Z",
        "until": "2026-01-12T00:00:00.000Z",
        "term": "lfx-2025-term2-follow-up",
        "weekOf": "2026-01-05"
      },
      "debug": "{\n  \"query\": \"query GetSummary($username: String!, $since: DateTime!, $until: DateTime!) {\\n    rateLimit {\\n        cost\\n        limit\\n        nodeCount\\n        remaining\\n        resetAt\\n        used\\n    }\\n    user(login:$username){\\n        login\\n        name\\n        contributionsCollection(from:$since, to:$until){\\n            startedAt\\n            endedAt\\n            hasAnyContributions\\n\\n            totalCommitContributions\\n            totalIssueContributions\\n            totalPullRequestContributions\\n            totalPullRequestReviewContributions\\n\\n            totalRepositoriesWithContributedCommits\\n            totalRepositoriesWithContributedIssues\\n\\n\\n            commitContributionsByRepository(maxRepositories:100){\\n                repository{\\n                    owner{\\n                        login\\n                    }\\n                    nameWithOwner\\n                    url\\n                }\\n                url\\n                contributions(first:100){\\n                    pageInfo{\\n                        hasNextPage\\n                    }\\n                    totalCount\\n                }\\n            }\\n            issueContributionsByRepository(maxRepositories:100){\\n                repository{\\n                    owner{\\n                        login\\n                    }\\n                    nameWithOwner\\n                    url\\n                }\\n                contributions(first:100){\\n                    pageInfo{\\n                        hasNextPage\\n                    }\\n                    totalCount\\n                    nodes{\\n                        issue{\\n                            number\\n                        }\\n                    }\\n                }\\n            }\\n            pullRequestContributionsByRepository(maxRepositories:100){\\n                repository{\\n                    owner{\\n                        login\\n                    }\\n                    nameWithOwner\\n                    url\\n                }\\n                contributions(first:100){\\n                    pageInfo{\\n                        hasNextPage\\n                    }\\n                    totalCount\\n                    nodes{\\n                        pullRequest{\\n                            number\\n                        }\\n                    }\\n                }\\n            }\\n            pullRequestReviewContributionsByRepository(maxRepositories:100){\\n                repository{\\n                    owner{\\n                        login\\n                    }\\n                    nameWithOwner\\n                    url\\n                }\\n                contributions(first:100){\\n                    pageInfo{\\n                        hasNextPage\\n                    }\\n                    totalCount\\n                    nodes{\\n                        pullRequestReview{\\n                            url\\n                            pullRequest{\\n                                number\\n                            }\\n                        }\\n                    }\\n                }\\n            }\\n        }\\n    }\\n}\",\n  \"variables\": {\n    \"username\": \"g4rud4kun\",\n    \"since\": \"2026-01-05T00:00:00.000Z\",\n    \"until\": \"2026-01-12T00:00:00.000Z\"\n  }\n}",
      "nonCriticalError": {
        "message": "Error in task 815e917b-ba4f-467a-ab61-29978b63aaf8: Request failed due to following response errors:\n - Could not resolve to a User with the login of 'g4rud4kun'.. Headers: {\"access-control-allow-origin\":\"*\",\"access-control-expose-headers\":\"ETag, Link, Location, Retry-After, X-GitHub-OTP, X-RateLimit-Limit, X-RateLimit-Remaining, X-RateLimit-Used, X-RateLimit-Resource, X-RateLimit-Reset, X-OAuth-Scopes, X-Accepted-OAuth-Scopes, X-Poll-Interval, X-GitHub-Media-Type, X-GitHub-SSO, X-GitHub-Request-Id, Deprecation, Sunset\",\"connection\":\"close\",\"content-encoding\":\"gzip\",\"content-security-policy\":\"default-src 'none'\",\"content-type\":\"application/json; charset=utf-8\",\"date\":\"Tue, 13 Jan 2026 08:47:41 GMT\",\"referrer-policy\":\"origin-when-cross-origin, strict-origin-when-cross-origin\",\"server\":\"github.com\",\"strict-transport-security\":\"max-age=31536000; includeSubdomains; preload\",\"transfer-encoding\":\"chunked\",\"vary\":\"Accept-Encoding, Accept, X-Requested-With\",\"x-accepted-oauth-scopes\":\"repo\",\"x-content-type-options\":\"nosniff\",\"x-frame-options\":\"deny\",\"x-github-media-type\":\"github.v3; format=json\",\"x-github-request-id\":\"644C:183FA8:124215:50CE37:696606AD\",\"x-oauth-scopes\":\"public_repo, read:org, read:user, repo:status, user:email\",\"x-ratelimit-limit\":\"5000\",\"x-ratelimit-remaining\":\"4955\",\"x-ratelimit-reset\":\"1768297541\",\"x-ratelimit-resource\":\"graphql\",\"x-ratelimit-used\":\"45\",\"x-xss-protection\":\"0\"}. Error: Could not resolve to a User with the login of 'g4rud4kun'.. Data: {\"rateLimit\":{\"cost\":1,\"limit\":5000,\"nodeCount\":400,\"remaining\":4955,\"resetAt\":\"2026-01-13T09:45:41Z\",\"used\":45},\"user\":null}.",
        "date": "2026-01-13T08:47:41.396Z"
      }
    },
    "825b26e5-62e9-42a9-9556-c69698628018": {
      "task": {
        "id": "825b26e5-62e9-42a9-9556-c69698628018",
        "parentId": null,
        "originatingTaskId": null,
        "username": "mukeshmahato17",
        "since": "2026-01-05T00:00:00.000Z",
        "until": "2026-01-12T00:00:00.000Z",
        "term": "lfx-2025-term2-follow-up",
        "weekOf": "2026-01-05"
      }
    },
    "82d4b933-42b2-4a74-8850-5d3ce9e09f8c": {
      "task": {
        "id": "82d4b933-42b2-4a74-8850-5d3ce9e09f8c",
        "parentId": null,
        "originatingTaskId": null,
        "username": "Naman-B-Parlecha",
        "since": "2026-01-05T00:00:00.000Z",
        "until": "2026-01-12T00:00:00.000Z",
        "term": "lfx-2025-term3-follow-up",
        "weekOf": "2026-01-05"
      }
    },
    "87bec5f6-b351-4e82-998c-106c9dabb98e": {
      "task": {
        "id": "87bec5f6-b351-4e82-998c-106c9dabb98e",
        "parentId": null,
        "originatingTaskId": null,
        "username": "vampirarte",
        "since": "2026-01-05T00:00:00.000Z",
        "until": "2026-01-12T00:00:00.000Z",
        "term": "lfx-2025-term3-follow-up",
        "weekOf": "2026-01-05"
      }
    },
    "89f81f99-7028-4b46-a136-e1907a9ad159": {
      "task": {
        "id": "89f81f99-7028-4b46-a136-e1907a9ad159",
        "parentId": null,
        "originatingTaskId": null,
        "username": "Daksh-10",
        "since": "2026-01-05T00:00:00.000Z",
        "until": "2026-01-12T00:00:00.000Z",
        "term": "lfx-2025-term1-follow-up",
        "weekOf": "2026-01-05"
      }
    },
    "8a20c20c-e0c5-4f8a-9304-994450a1b92e": {
      "task": {
        "id": "8a20c20c-e0c5-4f8a-9304-994450a1b92e",
        "parentId": null,
        "originatingTaskId": null,
        "username": "onkar717",
        "since": "2026-01-05T00:00:00.000Z",
        "until": "2026-01-12T00:00:00.000Z",
        "term": "lfx-2025-term1-follow-up",
        "weekOf": "2026-01-05"
      }
    },
    "8ce034b7-4d18-4154-8a49-8532b2e56fa3": {
      "task": {
        "id": "8ce034b7-4d18-4154-8a49-8532b2e56fa3",
        "parentId": null,
        "originatingTaskId": null,
        "username": "per0x1de-1337",
        "since": "2026-01-05T00:00:00.000Z",
        "until": "2026-01-12T00:00:00.000Z",
        "term": "lfx-2025-term3-follow-up",
        "weekOf": "2026-01-05"
      }
    },
    "8d0c889a-692f-4b7d-b17d-ee2083441d9d": {
      "task": {
        "id": "8d0c889a-692f-4b7d-b17d-ee2083441d9d",
        "parentId": null,
        "originatingTaskId": null,
        "username": "marcoma2018",
        "since": "2026-01-05T00:00:00.000Z",
        "until": "2026-01-12T00:00:00.000Z",
        "term": "lfx-2025-term3-follow-up",
        "weekOf": "2026-01-05"
      }
    },
    "8d164bc2-66f6-4771-bd12-1436d20fa940": {
      "task": {
        "id": "8d164bc2-66f6-4771-bd12-1436d20fa940",
        "parentId": null,
        "originatingTaskId": null,
        "username": "narharim",
        "since": "2026-01-05T00:00:00.000Z",
        "until": "2026-01-12T00:00:00.000Z",
        "term": "lfx-2025-term2-follow-up",
        "weekOf": "2026-01-05"
      }
    },
    "90d288cd-7037-44cb-b976-6e38afb2d491": {
      "task": {
        "id": "90d288cd-7037-44cb-b976-6e38afb2d491",
        "parentId": null,
        "originatingTaskId": null,
        "username": "andoriyaprashant",
        "since": "2026-01-05T00:00:00.000Z",
        "until": "2026-01-12T00:00:00.000Z",
        "term": "lfx-2025-term3-follow-up",
        "weekOf": "2026-01-05"
      }
    },
    "90f0b20a-374e-4789-8448-e9323ac21d4e": {
      "task": {
        "id": "90f0b20a-374e-4789-8448-e9323ac21d4e",
        "parentId": null,
        "originatingTaskId": null,
        "username": "Mohab96",
        "since": "2026-01-05T00:00:00.000Z",
        "until": "2026-01-12T00:00:00.000Z",
        "term": "lfx-2025-term3-follow-up",
        "weekOf": "2026-01-05"
      }
    },
    "921debec-18a3-40e4-9ec0-68737401dcc6": {
      "task": {
        "id": "921debec-18a3-40e4-9ec0-68737401dcc6",
        "parentId": null,
        "originatingTaskId": null,
        "username": "zrggw",
        "since": "2026-01-05T00:00:00.000Z",
        "until": "2026-01-12T00:00:00.000Z",
        "term": "lfx-2025-term3-follow-up",
        "weekOf": "2026-01-05"
      }
    },
    "92e7346d-213f-4050-8553-e6ec0af1359a": {
      "task": {
        "id": "92e7346d-213f-4050-8553-e6ec0af1359a",
        "parentId": null,
        "originatingTaskId": null,
        "username": "sneaxhuh",
        "since": "2026-01-05T00:00:00.000Z",
        "until": "2026-01-12T00:00:00.000Z",
        "term": "lfx-2025-term3-follow-up",
        "weekOf": "2026-01-05"
      }
    },
    "94451e93-5792-41aa-aa5d-37060b3ee225": {
      "task": {
        "id": "94451e93-5792-41aa-aa5d-37060b3ee225",
        "parentId": null,
        "originatingTaskId": null,
        "username": "SaxenaAnushka102",
        "since": "2026-01-05T00:00:00.000Z",
        "until": "2026-01-12T00:00:00.000Z",
        "term": "lfx-2025-term3-follow-up",
        "weekOf": "2026-01-05"
      }
    },
    "95c747eb-b680-4380-8667-fa248cc66ace": {
      "task": {
        "id": "95c747eb-b680-4380-8667-fa248cc66ace",
        "parentId": null,
        "originatingTaskId": null,
        "username": "winkletinkle",
        "since": "2026-01-05T00:00:00.000Z",
        "until": "2026-01-12T00:00:00.000Z",
        "term": "lfx-2025-term3-follow-up",
        "weekOf": "2026-01-05"
      }
    },
    "963c6e51-ddec-4707-8132-c0a227a03a7d": {
      "task": {
        "id": "963c6e51-ddec-4707-8132-c0a227a03a7d",
        "parentId": null,
        "originatingTaskId": null,
        "username": "alikhere",
        "since": "2026-01-05T00:00:00.000Z",
        "until": "2026-01-12T00:00:00.000Z",
        "term": "lfx-2025-term1-follow-up",
        "weekOf": "2026-01-05"
      }
    },
    "96cf9254-be57-4390-9707-9ab70e697bdf": {
      "task": {
        "id": "96cf9254-be57-4390-9707-9ab70e697bdf",
        "parentId": null,
        "originatingTaskId": null,
        "username": "fromsaurav",
        "since": "2026-01-05T00:00:00.000Z",
        "until": "2026-01-12T00:00:00.000Z",
        "term": "lfx-2025-term3-follow-up",
        "weekOf": "2026-01-05"
      }
    },
    "9754c879-0813-4e9c-b0b6-3571eb4b30db": {
      "task": {
        "id": "9754c879-0813-4e9c-b0b6-3571eb4b30db",
        "parentId": null,
        "originatingTaskId": null,
        "username": "vaibhaavv8",
        "since": "2026-01-05T00:00:00.000Z",
        "until": "2026-01-12T00:00:00.000Z",
        "term": "lfx-2025-term2-follow-up",
        "weekOf": "2026-01-05"
      }
    },
    "9a4f93b0-76fa-4aba-8787-e3dfb3fc1c36": {
      "task": {
        "id": "9a4f93b0-76fa-4aba-8787-e3dfb3fc1c36",
        "parentId": null,
        "originatingTaskId": null,
        "username": "nwanduka",
        "since": "2026-01-05T00:00:00.000Z",
        "until": "2026-01-12T00:00:00.000Z",
        "term": "lfx-2025-term1-follow-up",
        "weekOf": "2026-01-05"
      }
    },
    "9aac40c3-f8a5-41d6-aef5-687f9ee92d72": {
      "task": {
        "id": "9aac40c3-f8a5-41d6-aef5-687f9ee92d72",
        "parentId": null,
        "originatingTaskId": null,
        "username": "mounicasruthi",
        "since": "2026-01-05T00:00:00.000Z",
        "until": "2026-01-12T00:00:00.000Z",
        "term": "lfx-2025-term1-follow-up",
        "weekOf": "2026-01-05"
      }
    },
    "9aadb5bb-d16e-4c8c-b4b0-99c25e388fd7": {
      "task": {
        "id": "9aadb5bb-d16e-4c8c-b4b0-99c25e388fd7",
        "parentId": null,
        "originatingTaskId": null,
        "username": "abhishek-8081",
        "since": "2026-01-05T00:00:00.000Z",
        "until": "2026-01-12T00:00:00.000Z",
        "term": "lfx-2025-term3-follow-up",
        "weekOf": "2026-01-05"
      }
    },
    "9d5b8bd5-32c0-4523-b613-017627be65c5": {
      "task": {
        "id": "9d5b8bd5-32c0-4523-b613-017627be65c5",
        "parentId": null,
        "originatingTaskId": null,
        "username": "vickybesra",
        "since": "2026-01-05T00:00:00.000Z",
        "until": "2026-01-12T00:00:00.000Z",
        "term": "lfx-2025-term1-follow-up",
        "weekOf": "2026-01-05"
      }
    },
    "9e1c831b-b3e9-4cda-87cf-eb4e83c31d21": {
      "task": {
        "id": "9e1c831b-b3e9-4cda-87cf-eb4e83c31d21",
        "parentId": null,
        "originatingTaskId": null,
        "username": "mviswanathsai",
        "since": "2026-01-05T00:00:00.000Z",
        "until": "2026-01-12T00:00:00.000Z",
        "term": "lfx-2025-term1-follow-up",
        "weekOf": "2026-01-05"
      }
    },
    "9e24992f-bf49-436c-90fa-d1e40f44575d": {
      "task": {
        "id": "9e24992f-bf49-436c-90fa-d1e40f44575d",
        "parentId": null,
        "originatingTaskId": null,
        "username": "ainozaki",
        "since": "2026-01-05T00:00:00.000Z",
        "until": "2026-01-12T00:00:00.000Z",
        "term": "lfx-2025-term1-follow-up",
        "weekOf": "2026-01-05"
      }
    },
    "a08727b5-1248-4da2-a28c-e9ee6652f204": {
      "task": {
        "id": "a08727b5-1248-4da2-a28c-e9ee6652f204",
        "parentId": null,
        "originatingTaskId": null,
        "username": "Shrutim1505",
        "since": "2026-01-05T00:00:00.000Z",
        "until": "2026-01-12T00:00:00.000Z",
        "term": "lfx-2025-term1-follow-up",
        "weekOf": "2026-01-05"
      }
    },
    "a15f0435-f1d9-4930-a9dd-456b1031c0d3": {
      "task": {
        "id": "a15f0435-f1d9-4930-a9dd-456b1031c0d3",
        "parentId": null,
        "originatingTaskId": null,
        "username": "Emidowojo",
        "since": "2026-01-05T00:00:00.000Z",
        "until": "2026-01-12T00:00:00.000Z",
        "term": "lfx-2025-term2-follow-up",
        "weekOf": "2026-01-05"
      }
    },
    "a1e88616-b8b9-45ce-9b02-102235a6ec0e": {
      "task": {
        "id": "a1e88616-b8b9-45ce-9b02-102235a6ec0e",
        "parentId": null,
        "originatingTaskId": null,
        "username": "pokerfaceSad",
        "since": "2026-01-05T00:00:00.000Z",
        "until": "2026-01-12T00:00:00.000Z",
        "term": "lfx-2025-term3-follow-up",
        "weekOf": "2026-01-05"
      }
    },
    "a2b0599a-3064-40cb-a322-9c1947a38ba4": {
      "task": {
        "id": "a2b0599a-3064-40cb-a322-9c1947a38ba4",
        "parentId": null,
        "originatingTaskId": null,
        "username": "codered-lgtm",
        "since": "2026-01-05T00:00:00.000Z",
        "until": "2026-01-12T00:00:00.000Z",
        "term": "lfx-2025-term1-follow-up",
        "weekOf": "2026-01-05"
      }
    },
    "a3ecbceb-16a7-487b-9f6a-ccfc629f4382": {
      "task": {
        "id": "a3ecbceb-16a7-487b-9f6a-ccfc629f4382",
        "parentId": null,
        "originatingTaskId": null,
        "username": "GAURAV-DEEP01",
        "since": "2026-01-05T00:00:00.000Z",
        "until": "2026-01-12T00:00:00.000Z",
        "term": "lfx-2025-term3-follow-up",
        "weekOf": "2026-01-05"
      }
    },
    "a63859ce-c7aa-4c14-861c-f39807f4dc7f": {
      "task": {
        "id": "a63859ce-c7aa-4c14-861c-f39807f4dc7f",
        "parentId": null,
        "originatingTaskId": null,
        "username": "Praneeth-18",
        "since": "2026-01-05T00:00:00.000Z",
        "until": "2026-01-12T00:00:00.000Z",
        "term": "lfx-2025-term3-follow-up",
        "weekOf": "2026-01-05"
      }
    },
    "a7685e59-9076-4216-9c04-6581d4e052ae": {
      "task": {
        "id": "a7685e59-9076-4216-9c04-6581d4e052ae",
        "parentId": null,
        "originatingTaskId": null,
        "username": "codeahmedjamil",
        "since": "2026-01-05T00:00:00.000Z",
        "until": "2026-01-12T00:00:00.000Z",
        "term": "lfx-2025-term2-follow-up",
        "weekOf": "2026-01-05"
      }
    },
    "a7870941-5ab9-41b3-9d29-faa6807fb523": {
      "task": {
        "id": "a7870941-5ab9-41b3-9d29-faa6807fb523",
        "parentId": null,
        "originatingTaskId": null,
        "username": "ghadeer-elsalhawy",
        "since": "2026-01-05T00:00:00.000Z",
        "until": "2026-01-12T00:00:00.000Z",
        "term": "lfx-2025-term2-follow-up",
        "weekOf": "2026-01-05"
      }
    },
    "a7c288fe-abe5-4fda-bf36-b7bd96d64a0a": {
      "task": {
        "id": "a7c288fe-abe5-4fda-bf36-b7bd96d64a0a",
        "parentId": null,
        "originatingTaskId": null,
        "username": "AayushSaini101",
        "since": "2026-01-05T00:00:00.000Z",
        "until": "2026-01-12T00:00:00.000Z",
        "term": "lfx-2025-term2-follow-up",
        "weekOf": "2026-01-05"
      }
    },
    "adba8da8-8cd0-4b44-aeff-17e97c8ae7cd": {
      "task": {
        "id": "adba8da8-8cd0-4b44-aeff-17e97c8ae7cd",
        "parentId": null,
        "originatingTaskId": null,
        "username": "MichaelRren",
        "since": "2026-01-05T00:00:00.000Z",
        "until": "2026-01-12T00:00:00.000Z",
        "term": "lfx-2025-term2-follow-up",
        "weekOf": "2026-01-05"
      }
    },
    "add800c9-fc3e-4992-b36b-21b3c0e2ce76": {
      "task": {
        "id": "add800c9-fc3e-4992-b36b-21b3c0e2ce76",
        "parentId": null,
        "originatingTaskId": null,
        "username": "HaojieZhang6848",
        "since": "2026-01-05T00:00:00.000Z",
        "until": "2026-01-12T00:00:00.000Z",
        "term": "lfx-2025-term3-follow-up",
        "weekOf": "2026-01-05"
      }
    },
    "ae266d4c-07ec-45ee-bbac-df892f881112": {
      "task": {
        "id": "ae266d4c-07ec-45ee-bbac-df892f881112",
        "parentId": null,
        "originatingTaskId": null,
        "username": "miledxz",
        "since": "2026-01-05T00:00:00.000Z",
        "until": "2026-01-12T00:00:00.000Z",
        "term": "lfx-2025-term2-follow-up",
        "weekOf": "2026-01-05"
      }
    },
    "af8231e3-7a89-4509-97c6-c48173ecc49a": {
      "task": {
        "id": "af8231e3-7a89-4509-97c6-c48173ecc49a",
        "parentId": null,
        "originatingTaskId": null,
        "username": "sudiptob2",
        "since": "2026-01-05T00:00:00.000Z",
        "until": "2026-01-12T00:00:00.000Z",
        "term": "lfx-2025-term1-follow-up",
        "weekOf": "2026-01-05"
      }
    },
    "b3c7d3ff-55aa-4e02-a35a-16de4e0761d3": {
      "task": {
        "id": "b3c7d3ff-55aa-4e02-a35a-16de4e0761d3",
        "parentId": null,
        "originatingTaskId": null,
        "username": "perebaj",
        "since": "2026-01-05T00:00:00.000Z",
        "until": "2026-01-12T00:00:00.000Z",
        "term": "lfx-2025-term1-follow-up",
        "weekOf": "2026-01-05"
      }
    },
    "b5281315-2fe9-46b9-84a8-51564602ffb3": {
      "task": {
        "id": "b5281315-2fe9-46b9-84a8-51564602ffb3",
        "parentId": null,
        "originatingTaskId": null,
        "username": "Peacesandy",
        "since": "2026-01-05T00:00:00.000Z",
        "until": "2026-01-12T00:00:00.000Z",
        "term": "lfx-2025-term3-follow-up",
        "weekOf": "2026-01-05"
      }
    },
    "b53c5ae0-0540-47b5-b7fc-cc8b5f93e249": {
      "task": {
        "id": "b53c5ae0-0540-47b5-b7fc-cc8b5f93e249",
        "parentId": null,
        "originatingTaskId": null,
        "username": "Slideee",
        "since": "2026-01-05T00:00:00.000Z",
        "until": "2026-01-12T00:00:00.000Z",
        "term": "lfx-2025-term1-follow-up",
        "weekOf": "2026-01-05"
      }
    },
    "b60e0a96-17c6-43f2-b2d5-f94bb8559064": {
      "task": {
        "id": "b60e0a96-17c6-43f2-b2d5-f94bb8559064",
        "parentId": null,
        "originatingTaskId": null,
        "username": "mohdaquib171",
        "since": "2026-01-05T00:00:00.000Z",
        "until": "2026-01-12T00:00:00.000Z",
        "term": "lfx-2025-term1-follow-up",
        "weekOf": "2026-01-05"
      }
    },
    "b7a487a0-c7b2-498b-a6dd-650dd9576c9f": {
      "task": {
        "id": "b7a487a0-c7b2-498b-a6dd-650dd9576c9f",
        "parentId": null,
        "originatingTaskId": null,
        "username": "zihanKuang",
        "since": "2026-01-05T00:00:00.000Z",
        "until": "2026-01-12T00:00:00.000Z",
        "term": "lfx-2025-term2-follow-up",
        "weekOf": "2026-01-05"
      }
    },
    "b883fd19-bc3b-4116-92ea-5cb54d09dbaf": {
      "task": {
        "id": "b883fd19-bc3b-4116-92ea-5cb54d09dbaf",
        "parentId": null,
        "originatingTaskId": null,
        "username": "Darshan174",
        "since": "2026-01-05T00:00:00.000Z",
        "until": "2026-01-12T00:00:00.000Z",
        "term": "lfx-2025-term3-follow-up",
        "weekOf": "2026-01-05"
      }
    },
    "b8a4a09a-2926-48f2-bcf5-05071dd50358": {
      "task": {
        "id": "b8a4a09a-2926-48f2-bcf5-05071dd50358",
        "parentId": null,
        "originatingTaskId": null,
        "username": "ashish-dalal",
        "since": "2026-01-05T00:00:00.000Z",
        "until": "2026-01-12T00:00:00.000Z",
        "term": "lfx-2025-term3-follow-up",
        "weekOf": "2026-01-05"
      }
    },
    "b902da07-6214-4a34-b98f-c6b0ed57cb6e": {
      "task": {
        "id": "b902da07-6214-4a34-b98f-c6b0ed57cb6e",
        "parentId": null,
        "originatingTaskId": null,
        "username": "harsh-ps-2003",
        "since": "2026-01-05T00:00:00.000Z",
        "until": "2026-01-12T00:00:00.000Z",
        "term": "lfx-2025-term1-follow-up",
        "weekOf": "2026-01-05"
      }
    },
    "ba4e8ec5-2062-42d8-87d4-9c37ecdd0ffb": {
      "task": {
        "id": "ba4e8ec5-2062-42d8-87d4-9c37ecdd0ffb",
        "parentId": null,
        "originatingTaskId": null,
        "username": "amanycodes",
        "since": "2026-01-05T00:00:00.000Z",
        "until": "2026-01-12T00:00:00.000Z",
        "term": "lfx-2025-term2-follow-up",
        "weekOf": "2026-01-05"
      }
    },
    "ba79dca5-869d-4ba9-bf55-70596081ed8e": {
      "task": {
        "id": "ba79dca5-869d-4ba9-bf55-70596081ed8e",
        "parentId": null,
        "originatingTaskId": null,
        "username": "ballista01",
        "since": "2026-01-05T00:00:00.000Z",
        "until": "2026-01-12T00:00:00.000Z",
        "term": "lfx-2025-term3-follow-up",
        "weekOf": "2026-01-05"
      }
    },
    "bb63d9af-8b11-4e6b-8f46-d3a86de8ba68": {
      "task": {
        "id": "bb63d9af-8b11-4e6b-8f46-d3a86de8ba68",
        "parentId": null,
        "originatingTaskId": null,
        "username": "lavishpal",
        "since": "2026-01-05T00:00:00.000Z",
        "until": "2026-01-12T00:00:00.000Z",
        "term": "lfx-2025-term3-follow-up",
        "weekOf": "2026-01-05"
      }
    },
    "bc097faa-39f2-4ab7-8902-3137109b3f3d": {
      "task": {
        "id": "bc097faa-39f2-4ab7-8902-3137109b3f3d",
        "parentId": null,
        "originatingTaskId": null,
        "username": "qcserestipy",
        "since": "2026-01-05T00:00:00.000Z",
        "until": "2026-01-12T00:00:00.000Z",
        "term": "lfx-2025-term2-follow-up",
        "weekOf": "2026-01-05"
      }
    },
    "bdd14e31-ccee-4115-8b24-1117ba7ca793": {
      "task": {
        "id": "bdd14e31-ccee-4115-8b24-1117ba7ca793",
        "parentId": null,
        "originatingTaskId": null,
        "username": "vivekbisen04",
        "since": "2026-01-05T00:00:00.000Z",
        "until": "2026-01-12T00:00:00.000Z",
        "term": "lfx-2025-term2-follow-up",
        "weekOf": "2026-01-05"
      }
    },
    "bde01552-b621-46f9-b1bc-71226d45ae09": {
      "task": {
        "id": "bde01552-b621-46f9-b1bc-71226d45ae09",
        "parentId": null,
        "originatingTaskId": null,
        "username": "Paladian78",
        "since": "2026-01-05T00:00:00.000Z",
        "until": "2026-01-12T00:00:00.000Z",
        "term": "lfx-2025-term2-follow-up",
        "weekOf": "2026-01-05"
      }
    },
    "c0c42ee3-eba8-4d69-87f0-55debcf7a038": {
      "task": {
        "id": "c0c42ee3-eba8-4d69-87f0-55debcf7a038",
        "parentId": null,
        "originatingTaskId": null,
        "username": "Colvin-Y",
        "since": "2026-01-05T00:00:00.000Z",
        "until": "2026-01-12T00:00:00.000Z",
        "term": "lfx-2025-term3-follow-up",
        "weekOf": "2026-01-05"
      }
    },
    "c0ca64c4-5b55-44f4-bd73-1d3723ad030c": {
      "task": {
        "id": "c0ca64c4-5b55-44f4-bd73-1d3723ad030c",
        "parentId": null,
        "originatingTaskId": null,
        "username": "janithashri",
        "since": "2026-01-05T00:00:00.000Z",
        "until": "2026-01-12T00:00:00.000Z",
        "term": "lfx-2025-term3-follow-up",
        "weekOf": "2026-01-05"
      }
    },
    "c0fb9def-2bac-4308-bb11-60fd6f90c44e": {
      "task": {
        "id": "c0fb9def-2bac-4308-bb11-60fd6f90c44e",
        "parentId": null,
        "originatingTaskId": null,
        "username": "sagnik3788",
        "since": "2026-01-05T00:00:00.000Z",
        "until": "2026-01-12T00:00:00.000Z",
        "term": "lfx-2025-term2-follow-up",
        "weekOf": "2026-01-05"
      }
    },
    "c15af979-31d2-4e88-8f02-0158d9137a7d": {
      "task": {
        "id": "c15af979-31d2-4e88-8f02-0158d9137a7d",
        "parentId": null,
        "originatingTaskId": null,
        "username": "abhi0324",
        "since": "2026-01-05T00:00:00.000Z",
        "until": "2026-01-12T00:00:00.000Z",
        "term": "lfx-2025-term2-follow-up",
        "weekOf": "2026-01-05"
      }
    },
    "c2132c5b-ba42-4694-9c95-92724eb5a20d": {
      "task": {
        "id": "c2132c5b-ba42-4694-9c95-92724eb5a20d",
        "parentId": null,
        "originatingTaskId": null,
        "username": "Shaheer-Ahmd",
        "since": "2026-01-05T00:00:00.000Z",
        "until": "2026-01-12T00:00:00.000Z",
        "term": "lfx-2025-term1-follow-up",
        "weekOf": "2026-01-05"
      }
    },
    "c351e416-51cb-4dfc-9403-994a13326398": {
      "task": {
        "id": "c351e416-51cb-4dfc-9403-994a13326398",
        "parentId": null,
        "originatingTaskId": null,
        "username": "AdeshGhadage",
        "since": "2026-01-05T00:00:00.000Z",
        "until": "2026-01-12T00:00:00.000Z",
        "term": "lfx-2025-term1-follow-up",
        "weekOf": "2026-01-05"
      }
    },
    "c45b0e1b-154e-487c-a467-c74cfbd018c4": {
      "task": {
        "id": "c45b0e1b-154e-487c-a467-c74cfbd018c4",
        "parentId": null,
        "originatingTaskId": null,
        "username": "MdSayemkhan",
        "since": "2026-01-05T00:00:00.000Z",
        "until": "2026-01-12T00:00:00.000Z",
        "term": "lfx-2025-term1-follow-up",
        "weekOf": "2026-01-05"
      }
    },
    "c51dd731-b350-4008-93ae-5f7e7cc37c3f": {
      "task": {
        "id": "c51dd731-b350-4008-93ae-5f7e7cc37c3f",
        "parentId": null,
        "originatingTaskId": null,
        "username": "yashpandey06",
        "since": "2026-01-05T00:00:00.000Z",
        "until": "2026-01-12T00:00:00.000Z",
        "term": "lfx-2025-term1-follow-up",
        "weekOf": "2026-01-05"
      }
    },
    "c5f553ad-5503-4821-9748-7079bad67dcf": {
      "task": {
        "id": "c5f553ad-5503-4821-9748-7079bad67dcf",
        "parentId": null,
        "originatingTaskId": null,
        "username": "melsal13",
        "since": "2026-01-05T00:00:00.000Z",
        "until": "2026-01-12T00:00:00.000Z",
        "term": "lfx-2025-term1-follow-up",
        "weekOf": "2026-01-05"
      }
    },
    "c5f62ca4-d55b-4166-9077-05394f957ea8": {
      "task": {
        "id": "c5f62ca4-d55b-4166-9077-05394f957ea8",
        "parentId": null,
        "originatingTaskId": null,
        "username": "DeshDeepakKant",
        "since": "2026-01-05T00:00:00.000Z",
        "until": "2026-01-12T00:00:00.000Z",
        "term": "lfx-2025-term1-follow-up",
        "weekOf": "2026-01-05"
      }
    },
    "c756a5fd-2273-4ace-8cb9-1d5a91180ffa": {
      "task": {
        "id": "c756a5fd-2273-4ace-8cb9-1d5a91180ffa",
        "parentId": null,
        "originatingTaskId": null,
        "username": "PersistentJZH",
        "since": "2026-01-05T00:00:00.000Z",
        "until": "2026-01-12T00:00:00.000Z",
        "term": "lfx-2025-term3-follow-up",
        "weekOf": "2026-01-05"
      }
    },
    "c8a54952-8561-4ad3-b67e-b207d322899b": {
      "task": {
        "id": "c8a54952-8561-4ad3-b67e-b207d322899b",
        "parentId": null,
        "originatingTaskId": null,
        "username": "Vaishnav88sk",
        "since": "2026-01-05T00:00:00.000Z",
        "until": "2026-01-12T00:00:00.000Z",
        "term": "lfx-2025-term1-follow-up",
        "weekOf": "2026-01-05"
      }
    },
    "ca7f821c-c806-4a7b-a1e5-c462d692fa85": {
      "task": {
        "id": "ca7f821c-c806-4a7b-a1e5-c462d692fa85",
        "parentId": null,
        "originatingTaskId": null,
        "username": "anshRastogi02",
        "since": "2026-01-05T00:00:00.000Z",
        "until": "2026-01-12T00:00:00.000Z",
        "term": "lfx-2025-term2-follow-up",
        "weekOf": "2026-01-05"
      }
    },
    "cd96f75c-e8b4-4fcd-a9a1-a4eb3685022b": {
      "task": {
        "id": "cd96f75c-e8b4-4fcd-a9a1-a4eb3685022b",
        "parentId": null,
        "originatingTaskId": null,
        "username": "kushal9897",
        "since": "2026-01-05T00:00:00.000Z",
        "until": "2026-01-12T00:00:00.000Z",
        "term": "lfx-2025-term1-follow-up",
        "weekOf": "2026-01-05"
      }
    },
    "cf07bf89-5d81-466d-860e-2f9db9b8a499": {
      "task": {
        "id": "cf07bf89-5d81-466d-860e-2f9db9b8a499",
        "parentId": null,
        "originatingTaskId": null,
        "username": "vishruth-thimmaiah",
        "since": "2026-01-05T00:00:00.000Z",
        "until": "2026-01-12T00:00:00.000Z",
        "term": "lfx-2025-term2-follow-up",
        "weekOf": "2026-01-05"
      }
    },
    "d0796196-d0b1-4198-9fc9-9bf8caccd9e4": {
      "task": {
        "id": "d0796196-d0b1-4198-9fc9-9bf8caccd9e4",
        "parentId": null,
        "originatingTaskId": null,
        "username": "sachin21212121",
        "since": "2026-01-05T00:00:00.000Z",
        "until": "2026-01-12T00:00:00.000Z",
        "term": "lfx-2025-term2-follow-up",
        "weekOf": "2026-01-05"
      }
    },
    "d2df515b-51c9-4d3c-b674-281e738c5ddf": {
      "task": {
        "id": "d2df515b-51c9-4d3c-b674-281e738c5ddf",
        "parentId": null,
        "originatingTaskId": null,
        "username": "XploY04",
        "since": "2026-01-05T00:00:00.000Z",
        "until": "2026-01-12T00:00:00.000Z",
        "term": "lfx-2025-term3-follow-up",
        "weekOf": "2026-01-05"
      }
    },
    "d3434742-e041-4d69-91c0-fc38e17e7045": {
      "task": {
        "id": "d3434742-e041-4d69-91c0-fc38e17e7045",
        "parentId": null,
        "originatingTaskId": null,
        "username": "E-STAT",
        "since": "2026-01-05T00:00:00.000Z",
        "until": "2026-01-12T00:00:00.000Z",
        "term": "lfx-2025-term3-follow-up",
        "weekOf": "2026-01-05"
      }
    },
    "d4c4e7a7-3c32-4d65-863b-e1ced902726c": {
      "task": {
        "id": "d4c4e7a7-3c32-4d65-863b-e1ced902726c",
        "parentId": null,
        "originatingTaskId": null,
        "username": "meethereum",
        "since": "2026-01-05T00:00:00.000Z",
        "until": "2026-01-12T00:00:00.000Z",
        "term": "lfx-2025-term3-follow-up",
        "weekOf": "2026-01-05"
      }
    },
    "d7ff430c-bd11-4777-a810-2b8ab6447625": {
      "task": {
        "id": "d7ff430c-bd11-4777-a810-2b8ab6447625",
        "parentId": null,
        "originatingTaskId": null,
        "username": "NucleoFusion",
        "since": "2026-01-05T00:00:00.000Z",
        "until": "2026-01-12T00:00:00.000Z",
        "term": "lfx-2025-term3-follow-up",
        "weekOf": "2026-01-05"
      }
    },
    "d8348bcf-8884-4d73-9b9e-42ffd4fa9a33": {
      "task": {
        "id": "d8348bcf-8884-4d73-9b9e-42ffd4fa9a33",
        "parentId": null,
        "originatingTaskId": null,
        "username": "harish2773",
        "since": "2026-01-05T00:00:00.000Z",
        "until": "2026-01-12T00:00:00.000Z",
        "term": "lfx-2025-term2-follow-up",
        "weekOf": "2026-01-05"
      },
      "debug": "{\n  \"query\": \"query GetSummary($username: String!, $since: DateTime!, $until: DateTime!) {\\n    rateLimit {\\n        cost\\n        limit\\n        nodeCount\\n        remaining\\n        resetAt\\n        used\\n    }\\n    user(login:$username){\\n        login\\n        name\\n        contributionsCollection(from:$since, to:$until){\\n            startedAt\\n            endedAt\\n            hasAnyContributions\\n\\n            totalCommitContributions\\n            totalIssueContributions\\n            totalPullRequestContributions\\n            totalPullRequestReviewContributions\\n\\n            totalRepositoriesWithContributedCommits\\n            totalRepositoriesWithContributedIssues\\n\\n\\n            commitContributionsByRepository(maxRepositories:100){\\n                repository{\\n                    owner{\\n                        login\\n                    }\\n                    nameWithOwner\\n                    url\\n                }\\n                url\\n                contributions(first:100){\\n                    pageInfo{\\n                        hasNextPage\\n                    }\\n                    totalCount\\n                }\\n            }\\n            issueContributionsByRepository(maxRepositories:100){\\n                repository{\\n                    owner{\\n                        login\\n                    }\\n                    nameWithOwner\\n                    url\\n                }\\n                contributions(first:100){\\n                    pageInfo{\\n                        hasNextPage\\n                    }\\n                    totalCount\\n                    nodes{\\n                        issue{\\n                            number\\n                        }\\n                    }\\n                }\\n            }\\n            pullRequestContributionsByRepository(maxRepositories:100){\\n                repository{\\n                    owner{\\n                        login\\n                    }\\n                    nameWithOwner\\n                    url\\n                }\\n                contributions(first:100){\\n                    pageInfo{\\n                        hasNextPage\\n                    }\\n                    totalCount\\n                    nodes{\\n                        pullRequest{\\n                            number\\n                        }\\n                    }\\n                }\\n            }\\n            pullRequestReviewContributionsByRepository(maxRepositories:100){\\n                repository{\\n                    owner{\\n                        login\\n                    }\\n                    nameWithOwner\\n                    url\\n                }\\n                contributions(first:100){\\n                    pageInfo{\\n                        hasNextPage\\n                    }\\n                    totalCount\\n                    nodes{\\n                        pullRequestReview{\\n                            url\\n                            pullRequest{\\n                                number\\n                            }\\n                        }\\n                    }\\n                }\\n            }\\n        }\\n    }\\n}\",\n  \"variables\": {\n    \"username\": \"harish2773\",\n    \"since\": \"2026-01-05T00:00:00.000Z\",\n    \"until\": \"2026-01-12T00:00:00.000Z\"\n  }\n}",
      "nonCriticalError": {
        "message": "Error in task d8348bcf-8884-4d73-9b9e-42ffd4fa9a33: Request failed due to following response errors:\n - Could not resolve to a User with the login of 'harish2773'.. Headers: {\"access-control-allow-origin\":\"*\",\"access-control-expose-headers\":\"ETag, Link, Location, Retry-After, X-GitHub-OTP, X-RateLimit-Limit, X-RateLimit-Remaining, X-RateLimit-Used, X-RateLimit-Resource, X-RateLimit-Reset, X-OAuth-Scopes, X-Accepted-OAuth-Scopes, X-Poll-Interval, X-GitHub-Media-Type, X-GitHub-SSO, X-GitHub-Request-Id, Deprecation, Sunset\",\"connection\":\"close\",\"content-encoding\":\"gzip\",\"content-security-policy\":\"default-src 'none'\",\"content-type\":\"application/json; charset=utf-8\",\"date\":\"Tue, 13 Jan 2026 08:46:41 GMT\",\"referrer-policy\":\"origin-when-cross-origin, strict-origin-when-cross-origin\",\"server\":\"github.com\",\"strict-transport-security\":\"max-age=31536000; includeSubdomains; preload\",\"transfer-encoding\":\"chunked\",\"vary\":\"Accept-Encoding, Accept, X-Requested-With\",\"x-accepted-oauth-scopes\":\"repo\",\"x-content-type-options\":\"nosniff\",\"x-frame-options\":\"deny\",\"x-github-media-type\":\"github.v3; format=json\",\"x-github-request-id\":\"644C:D838E:2D186D1:C517882:69660671\",\"x-oauth-scopes\":\"public_repo, read:org, read:user, repo:status, user:email\",\"x-ratelimit-limit\":\"5000\",\"x-ratelimit-remaining\":\"4975\",\"x-ratelimit-reset\":\"1768297541\",\"x-ratelimit-resource\":\"graphql\",\"x-ratelimit-used\":\"25\",\"x-xss-protection\":\"0\"}. Error: Could not resolve to a User with the login of 'harish2773'.. Data: {\"rateLimit\":{\"cost\":1,\"limit\":5000,\"nodeCount\":400,\"remaining\":4975,\"resetAt\":\"2026-01-13T09:45:41Z\",\"used\":25},\"user\":null}.",
        "date": "2026-01-13T08:46:41.393Z"
      }
    },
    "da85f5b1-06ed-421b-a62c-05b093e9f481": {
      "task": {
        "id": "da85f5b1-06ed-421b-a62c-05b093e9f481",
        "parentId": null,
        "originatingTaskId": null,
        "username": "EdwinaZhu",
        "since": "2026-01-05T00:00:00.000Z",
        "until": "2026-01-12T00:00:00.000Z",
        "term": "lfx-2025-term2-follow-up",
        "weekOf": "2026-01-05"
      }
    },
    "dafece92-c022-407a-86a8-098f8c41b94e": {
      "task": {
        "id": "dafece92-c022-407a-86a8-098f8c41b94e",
        "parentId": null,
        "originatingTaskId": null,
        "username": "Eeshu-Yadav",
        "since": "2026-01-05T00:00:00.000Z",
        "until": "2026-01-12T00:00:00.000Z",
        "term": "lfx-2025-term3-follow-up",
        "weekOf": "2026-01-05"
      }
    },
    "dd8ed420-dc9e-40df-8555-6c55f3380ea9": {
      "task": {
        "id": "dd8ed420-dc9e-40df-8555-6c55f3380ea9",
        "parentId": null,
        "originatingTaskId": null,
        "username": "sridamul",
        "since": "2026-01-05T00:00:00.000Z",
        "until": "2026-01-12T00:00:00.000Z",
        "term": "lfx-2025-term1-follow-up",
        "weekOf": "2026-01-05"
      }
    },
    "dea2e21f-e9af-445d-b334-233d642342c2": {
      "task": {
        "id": "dea2e21f-e9af-445d-b334-233d642342c2",
        "parentId": null,
        "originatingTaskId": null,
        "username": "AishwaryaGhatole2102",
        "since": "2026-01-05T00:00:00.000Z",
        "until": "2026-01-12T00:00:00.000Z",
        "term": "lfx-2025-term2-follow-up",
        "weekOf": "2026-01-05"
      }
    },
    "df094956-f9ea-44fe-a496-0bb93fd063c4": {
      "task": {
        "id": "df094956-f9ea-44fe-a496-0bb93fd063c4",
        "parentId": null,
        "originatingTaskId": null,
        "username": "Acuspeedster",
        "since": "2026-01-05T00:00:00.000Z",
        "until": "2026-01-12T00:00:00.000Z",
        "term": "lfx-2025-term1-follow-up",
        "weekOf": "2026-01-05"
      }
    },
    "e56a456e-acc9-44e6-b627-8773eb803464": {
      "task": {
        "id": "e56a456e-acc9-44e6-b627-8773eb803464",
        "parentId": null,
        "originatingTaskId": null,
        "username": "dhimanAbhi",
        "since": "2026-01-05T00:00:00.000Z",
        "until": "2026-01-12T00:00:00.000Z",
        "term": "lfx-2025-term2-follow-up",
        "weekOf": "2026-01-05"
      }
    },
    "e5748188-8205-4bed-bf6d-84c70be1e93e": {
      "task": {
        "id": "e5748188-8205-4bed-bf6d-84c70be1e93e",
        "parentId": null,
        "originatingTaskId": null,
        "username": "neolit123",
        "since": "2026-01-05T00:00:00.000Z",
        "until": "2026-01-12T00:00:00.000Z",
        "term": "lfx-2025-term3-follow-up",
        "weekOf": "2026-01-05"
      }
    },
    "e6abe38f-3506-4af0-858d-541b98876817": {
      "task": {
        "id": "e6abe38f-3506-4af0-858d-541b98876817",
        "parentId": null,
        "originatingTaskId": null,
        "username": "vishvamsinh28",
        "since": "2026-01-05T00:00:00.000Z",
        "until": "2026-01-12T00:00:00.000Z",
        "term": "lfx-2025-term2-follow-up",
        "weekOf": "2026-01-05"
      }
    },
    "e7ac5d5c-9c6d-48f6-86b3-44d70bb5a80a": {
      "task": {
        "id": "e7ac5d5c-9c6d-48f6-86b3-44d70bb5a80a",
        "parentId": null,
        "originatingTaskId": null,
        "username": "IcyFeather233",
        "since": "2026-01-05T00:00:00.000Z",
        "until": "2026-01-12T00:00:00.000Z",
        "term": "lfx-2025-term1-follow-up",
        "weekOf": "2026-01-05"
      }
    },
    "e8d54601-97cf-4ba6-a9f0-a55a0520f6b1": {
      "task": {
        "id": "e8d54601-97cf-4ba6-a9f0-a55a0520f6b1",
        "parentId": null,
        "originatingTaskId": null,
        "username": "partik03",
        "since": "2026-01-05T00:00:00.000Z",
        "until": "2026-01-12T00:00:00.000Z",
        "term": "lfx-2025-term3-follow-up",
        "weekOf": "2026-01-05"
      }
    },
    "eb6ef603-2785-4a62-9a24-85b6e38cf8c9": {
      "task": {
        "id": "eb6ef603-2785-4a62-9a24-85b6e38cf8c9",
        "parentId": null,
        "originatingTaskId": null,
        "username": "manzil-infinity180",
        "since": "2026-01-05T00:00:00.000Z",
        "until": "2026-01-12T00:00:00.000Z",
        "term": "lfx-2025-term1-follow-up",
        "weekOf": "2026-01-05"
      }
    },
    "eee578a3-cee5-4eb5-8218-4eadfbc8e77e": {
      "task": {
        "id": "eee578a3-cee5-4eb5-8218-4eadfbc8e77e",
        "parentId": null,
        "originatingTaskId": null,
        "username": "jason810496",
        "since": "2026-01-05T00:00:00.000Z",
        "until": "2026-01-12T00:00:00.000Z",
        "term": "lfx-2025-term2-follow-up",
        "weekOf": "2026-01-05"
      }
    },
    "eef1ad6a-02bc-465f-9c5e-e95b3eb61233": {
      "task": {
        "id": "eef1ad6a-02bc-465f-9c5e-e95b3eb61233",
        "parentId": null,
        "originatingTaskId": null,
        "username": "oksaumya",
        "since": "2026-01-05T00:00:00.000Z",
        "until": "2026-01-12T00:00:00.000Z",
        "term": "lfx-2025-term2-follow-up",
        "weekOf": "2026-01-05"
      }
    },
    "f15f6a31-adfa-4724-82bb-1f05bc19f321": {
      "task": {
        "id": "f15f6a31-adfa-4724-82bb-1f05bc19f321",
        "parentId": null,
        "originatingTaskId": null,
        "username": "btwshivam",
        "since": "2026-01-05T00:00:00.000Z",
        "until": "2026-01-12T00:00:00.000Z",
        "term": "lfx-2025-term2-follow-up",
        "weekOf": "2026-01-05"
      }
    },
    "f3263896-a928-419a-86e9-7113d8f05f18": {
      "task": {
        "id": "f3263896-a928-419a-86e9-7113d8f05f18",
        "parentId": null,
        "originatingTaskId": null,
        "username": "vatsalkeshav",
        "since": "2026-01-05T00:00:00.000Z",
        "until": "2026-01-12T00:00:00.000Z",
        "term": "lfx-2025-term2-follow-up",
        "weekOf": "2026-01-05"
      }
    },
    "f32b4e95-0652-4f5f-b566-f7d0f5168a94": {
      "task": {
        "id": "f32b4e95-0652-4f5f-b566-f7d0f5168a94",
        "parentId": null,
        "originatingTaskId": null,
        "username": "SinghaAnirban005",
        "since": "2026-01-05T00:00:00.000Z",
        "until": "2026-01-12T00:00:00.000Z",
        "term": "lfx-2025-term2-follow-up",
        "weekOf": "2026-01-05"
      }
    },
    "f4600b08-d1aa-4966-b93f-c81f7b9446ef": {
      "task": {
        "id": "f4600b08-d1aa-4966-b93f-c81f7b9446ef",
        "parentId": null,
        "originatingTaskId": null,
        "username": "sorabhopps",
        "since": "2026-01-05T00:00:00.000Z",
        "until": "2026-01-12T00:00:00.000Z",
        "term": "lfx-2025-term3-follow-up",
        "weekOf": "2026-01-05"
      }
    },
    "f544427d-2922-4618-8b12-9aa2c9d8f1f6": {
      "task": {
        "id": "f544427d-2922-4618-8b12-9aa2c9d8f1f6",
        "parentId": null,
        "originatingTaskId": null,
        "username": "neolit123",
        "since": "2026-01-05T00:00:00.000Z",
        "until": "2026-01-12T00:00:00.000Z",
        "term": "lfx-2025-term2-follow-up",
        "weekOf": "2026-01-05"
      }
    },
    "f9cdaeb4-7f3a-41d7-a961-edc346a8a1f3": {
      "task": {
        "id": "f9cdaeb4-7f3a-41d7-a961-edc346a8a1f3",
        "parentId": null,
        "originatingTaskId": null,
        "username": "MAVRICK-1",
        "since": "2026-01-05T00:00:00.000Z",
        "until": "2026-01-12T00:00:00.000Z",
        "term": "lfx-2025-term1-follow-up",
        "weekOf": "2026-01-05"
      }
    },
    "fabd420c-145a-4153-b281-5c587fb85efe": {
      "task": {
        "id": "fabd420c-145a-4153-b281-5c587fb85efe",
        "parentId": null,
        "originatingTaskId": null,
        "username": "slashexx",
        "since": "2026-01-05T00:00:00.000Z",
        "until": "2026-01-12T00:00:00.000Z",
        "term": "lfx-2025-term3-follow-up",
        "weekOf": "2026-01-05"
      }
    },
    "fcd3fcd6-2bc4-4209-a07a-16800c45a9e6": {
      "task": {
        "id": "fcd3fcd6-2bc4-4209-a07a-16800c45a9e6",
        "parentId": null,
        "originatingTaskId": null,
        "username": "krishi-agrawal",
        "since": "2026-01-05T00:00:00.000Z",
        "until": "2026-01-12T00:00:00.000Z",
        "term": "lfx-2025-term1-follow-up",
        "weekOf": "2026-01-05"
      }
    },
    "fce05e9d-1238-43a6-8a0a-1411b610f6ab": {
      "task": {
        "id": "fce05e9d-1238-43a6-8a0a-1411b610f6ab",
        "parentId": null,
        "originatingTaskId": null,
        "username": "mahdikhashan",
        "since": "2026-01-05T00:00:00.000Z",
        "until": "2026-01-12T00:00:00.000Z",
        "term": "lfx-2025-term2-follow-up",
        "weekOf": "2026-01-05"
      }
    },
    "fd8fe9d7-e136-404f-ac54-ccdd528e94bd": {
      "task": {
        "id": "fd8fe9d7-e136-404f-ac54-ccdd528e94bd",
        "parentId": null,
        "originatingTaskId": null,
        "username": "Mohdcode",
        "since": "2026-01-05T00:00:00.000Z",
        "until": "2026-01-12T00:00:00.000Z",
        "term": "lfx-2025-term1-follow-up",
        "weekOf": "2026-01-05"
      }
    },
    "fe8fa32b-f4af-4e6d-8a8f-a0fb0dd54549": {
      "task": {
        "id": "fe8fa32b-f4af-4e6d-8a8f-a0fb0dd54549",
        "parentId": null,
        "originatingTaskId": null,
        "username": "danish9039",
        "since": "2026-01-05T00:00:00.000Z",
        "until": "2026-01-12T00:00:00.000Z",
        "term": "lfx-2025-term3-follow-up",
        "weekOf": "2026-01-05"
      }
    },
    "ffcf97d7-9b91-4e13-ae7f-e58e9667e478": {
      "task": {
        "id": "ffcf97d7-9b91-4e13-ae7f-e58e9667e478",
        "parentId": null,
        "originatingTaskId": null,
        "username": "DoisLONG",
        "since": "2026-01-05T00:00:00.000Z",
        "until": "2026-01-12T00:00:00.000Z",
        "term": "lfx-2025-term1-follow-up",
        "weekOf": "2026-01-05"
      }
    }
  },
  "errored": {},
  "archived": {}
}